Workbook

Sheet 📦 Registro
A1: 🖥️ REGISTRO COMPLETO DE OPERACIONES — REVENTA DE TECNOLOGÍA
A2: Registra TODOS los equipos aquí. El Stock activo se actualiza solo en la hoja 📋 Stock.
A3: ID | B3: Categoría | C3: Fecha Compra | D3: Equipo | E3: Marca | F3: Modelo | G3: Bateria | H3: IMEI / S/N | I3: Estado Equipo | J3: Proveedor | K3: Forma Pago Compra | L3: Precio Compra | M3: Gastos Extra | N3: Costo Total | O3: Fecha Venta | P3: Plataforma Venta | Q3: Precio Venta | R3: Ganancia Neta | S3: Comentarios
A4: =IF(D4<>"",ROW()-3,"") -> 1 | B4: Smartphone | C4: 46165 | D4: HUAWEI NOVA 14 PRO | E4: HUAWEI | F4: NOVA 14 PRO | G4: 100 | H4: 867545070236530/867545070240581 | I4: Como nuevo | J4: BYRON MUÑOZ/WUKONGS TORE | K4: Transferencia | L4: 230000 | N4: =IF(L4<>"",L4+IF(M4<>"",M4,0),"") -> 230000 | O4: 46195 | P4: Facebook Marketplace | Q4: 230000 | R4: =IF(Q4<>"",Q4-IF(N4<>"",N4,0),"") -> 0 | S4: =IF(Q4<>"",Q4-IF(N4<>"",N4,0),"") -> 0
A5: =IF(D5<>"",ROW()-3,"") -> 2 | B5: Smartphone | C5: 46161 | D5: REDMI NOTE 13 PRO PLUS - IMEI 2 - TAPA TRIZADA | E5: XIAOMI | F5: REDMI NOTE 13 PRO PUS | H5: 868451068875703 - 868451068875711 | I5: Con falla | J5: JOSE ANTONIO LLAULEN | K5: Transferencia | L5: 50000 | N5: 50000 | O5: 46185 | P5: Presencial | Q5: 100000 | R5: =IF(Q5<>"",Q5-IF(N5<>"",N5,0),"") -> 50000 | S5: =IF(Q5<>"",Q5-IF(N5<>"",N5,0),"") -> 50000
A6: =IF(D6<>"",ROW()-3,"") -> 3 | B6: Smartphone | C6: 46161 | D6: SAMSUNG GALAXY A55 8/128 | E6: SAMSUNG | F6: GALAXY A55 | H6: 357042144369411 - 357695574369415 | I6: Con falla | J6: JOSE ANTONIO LLAULEN | K6: Transferencia | L6: 50000 | N6: =IF(L6<>"",L6+IF(M6<>"",M6,0),"") -> 50000 | O6: 46194 | P6: Facebook Marketplace | Q6: 70000 | S6: =IF(Q6<>"",Q6-IF(N6<>"",N6,0),"") -> 20000
A7: =IF(D7<>"",ROW()-3,"") -> 4 | B7: Smartphone | C7: 46170 | D7: APPLE IPHONE 14 PRO 256GB | E7: APPLE | F7: IPHONE 14 PRO | G7: 0.87 | H7: 358996914951899 - 358996914594772 | I7: Como nuevo | J7: CARLOS ALBERTO BRUNA RAMOS | K7: Transferencia | L7: 250000 | N7: =IF(L7<>"",L7+IF(M7<>"",M7,0),"") -> 250000 | O7: 46197 | P7: Facebook Marketplace | Q7: 370000 | S7: =IF(Q7<>"",Q7-IF(N7<>"",N7,0),"") -> 120000
A8: =IF(D8<>"",ROW()-3,"") -> 5 | B8: Smartphone | C8: 46170 | D8: APPLE IPHONE 11 PRO 64GB | E8: APPLE | F8: IPHONE 11 PRO | G8: 0.86 | I8: Con falla | J8: CARLOS ALBERTO BRUNA RAMOS | K8: Transferencia | L8: 20000 | N8: =IF(L8<>"",L8+IF(M8<>"",M8,0),"") -> 20000 | R8: =IF(Q8<>"",Q8-IF(N8<>"",N8,0),"") | S8: =IF(Q8<>"",Q8-IF(N8<>"",N8,0),"")
A9: =IF(D9<>"",ROW()-3,"") -> 6 | B9: Smartphone | C9: 46170 | D9: HONOR POWER 2 12/256 | E9: HONOR | F9: POWER 2 | G9: 1 | H9: 862304082444186/:862304082517940 | I9: Como nuevo | J9: EDSON | K9: Transferencia | L9: 80000 | N9: =IF(L9<>"",L9+IF(M9<>"",M9,0),"") -> 80000 | O9: 46213 | P9: Presencial | Q9: 150000 | S9: =IF(Q9<>"",Q9-IF(N9<>"",N9,0),"") -> 70000
A10: =IF(D10<>"",ROW()-3,"") -> 7 | B10: Notebook | C10: 46125 | D10: ASUS PROART STUDIOBOOK I9/64 GB | E10: ASUS | F10: PROART | I10: Como nuevo | J10: EDSON | K10: Transferencia | L10: 850000 | N10: =IF(L10<>"",L10+IF(M10<>"",M10,0),"") -> 850000 | S10: =IF(Q10<>"",Q10-IF(N10<>"",N10,0),"")
A11: =IF(D11<>"",ROW()-3,"") -> 8 | B11: Notebook | C11: 46182 | D11: LENOVO THINKBOOK P16 GEN 2 | E11: LENOVO | F11: THINKBOOK P16 GEN 2 | I11: Como nuevo | J11: DIEGO | K11: Transferencia | L11: 480000 | N11: =IF(L11<>"",L11+IF(M11<>"",M11,0),"") -> 480000 | S11: =IF(Q11<>"",Q11-IF(N11<>"",N11,0),"")
A12: =IF(D12<>"",ROW()-3,"") -> 9 | B12: Notebook | C12: 46183 | D12: LENOVO LEGION 5 I7/32GB/1TB | E12: LENOVO | F12: LEGION 5 | I12: Bueno | J12: FRANCISCO | K12: Transferencia | L12: 204000 | N12: =IF(L12<>"",L12+IF(M12<>"",M12,0),"") -> 204000 | O12: 46185 | P12: Facebook Marketplace | Q12: 300000 | S12: =IF(Q12<>"",Q12-IF(N12<>"",N12,0),"") -> 96000
A13: =IF(D13<>"",ROW()-3,"") -> 10 | B13: Notebook | C13: 46181 | D13: DELL VOSTRO 3405 RYZEN 5 | E13: DELL | F13: VOSTRO | I13: Con falla | J13: ANALYS | K13: Transferencia | L13: 50000 | N13: =IF(L13<>"",L13+IF(M13<>"",M13,0),"") -> 50000 | S13: =IF(Q13<>"",Q13-IF(N13<>"",N13,0),"")
A14: =IF(D14<>"",ROW()-3,"") -> 11 | B14: Smartwatch | C14: 46170 | D14: APPLE WATCH SE GEN 2 44M + CELLULAR | E14: APPLE | F14: SE GEN 2 44M | G14: 100 | I14: Como nuevo | J14: CARLOS | K14: MercadoPago | L14: 50000 | N14: =IF(L14<>"",L14+IF(M14<>"",M14,0),"") -> 50000 | S14: =IF(Q14<>"",Q14-IF(N14<>"",N14,0),"")
A15: =IF(D15<>"",ROW()-3,"") -> 12 | B15: Computador | C15: 46147 | D15: LENOVO THINKCENTRE M70Q GEN 6 | E15: LENOVO | F15: THINKCENTRE M70Q GEN 6 | I15: Nuevo | J15: MATIAS | K15: MercadoPago | L15: 300000 | N15: =IF(L15<>"",L15+IF(M15<>"",M15,0),"") -> 300000 | S15: =IF(Q15<>"",Q15-IF(N15<>"",N15,0),"")
A16: =IF(D16<>"",ROW()-3,"") -> 13 | B16: Computador | C16: 46101 | D16: TORRE THREADRIPPER | E16: MSI | F16: GENERICO | I16: Bueno | J16: PATRICIO | K16: Transferencia | L16: 320000 | N16: =IF(L16<>"",L16+IF(M16<>"",M16,0),"") -> 320000 | S16: =IF(Q16<>"",Q16-IF(N16<>"",N16,0),"")
A17: =IF(D17<>"",ROW()-3,"") -> 14 | B17: Computador | C17: 46185 | D17: CPU RYZEN 7 3700X, 1660TI | E17: COOLERMASTER | F17: GENERICO | I17: Bueno | J17: VICENTE TOMAS SANDOBAL GOMEZ | K17: Transferencia | L17: 210000 | N17: =IF(L17<>"",L17+IF(M17<>"",M17,0),"") -> 210000 | O17: 46193 | P17: Presencial | Q17: 361000 | S17: =IF(Q17<>"",Q17-IF(N17<>"",N17,0),"") -> 151000
A18: =IF(D18<>"",ROW()-3,"") -> 15 | B18: Smartphone | C18: 46190 | D18: REDMI NOTE 15 PRO 512GB | E18: XIAOMI | F18: REDMI NOTE 15 PRO | G18: 100 | I18: Como nuevo | J18: VICTOR MESARINO | K18: Transferencia | L18: 100000 | N18: =IF(L18<>"",L18+IF(M18<>"",M18,0),"") -> 100000 | O18: 46190 | P18: Presencial | Q18: 150000 | S18: =IF(Q18<>"",Q18-IF(N18<>"",N18,0),"") -> 50000
A19: =IF(D19<>"",ROW()-3,"") -> 16 | B19: Computador | C19: 46194 | D19: DELL LATITUDE 3240 | E19: DELL | F19: LATITUDE 3420 | I19: Como nuevo | J19: FERNAND LIOPEZ ESPINOZA | K19: Efectivo | L19: 80000 | N19: =IF(L19<>"",L19+IF(M19<>"",M19,0),"") -> 80000 | S19: =IF(Q19<>"",Q19-IF(N19<>"",N19,0),"")
A20: =IF(D20<>"",ROW()-3,"") -> 17 | B20: Smartphone | C20: 46200 | D20: SAMSUNG GALAXY A07 | E20: SAMSUNG | F20: GALAXY A07 | I20: Como nuevo | J20: JOSE PANCHO DIAZ | K20: Efectivo | L20: 40000 | N20: =IF(L20<>"",L20+IF(M20<>"",M20,0),"") -> 40000 | O20: 46203 | P20: Presencial | Q20: 80000 | S20: =IF(Q20<>"",Q20-IF(N20<>"",N20,0),"") -> 40000
A21: =IF(D21<>"",ROW()-3,"") -> 18 | B21: Smartphone | C21: 46195 | D21: APPLE IPHONE 14 PRO MAX 256GB | E21: APPLE | F21: 14 PRO MAX | G21: 89 | I21: Bueno | J21: MAU | K21: Otro | L21: 230000 | N21: =IF(L21<>"",L21+IF(M21<>"",M21,0),"") -> 230000 | O21: 46215 | P21: Presencial | Q21: 200000 | S21: =IF(Q21<>"",Q21-IF(N21<>"",N21,0),"") -> -30000
A22: =IF(D22<>"",ROW()-3,"") -> 19 | B22: Smartphone | C22: 46198 | D22: MOTOROLA MOTO G86 POWER | E22: MOTOROLA | F22: G86 POWER | I22: Bueno | J22: ANITA | K22: Efectivo | L22: 60000 | N22: =IF(L22<>"",L22+IF(M22<>"",M22,0),"") -> 60000 | S22: =IF(Q22<>"",Q22-IF(N22<>"",N22,0),"")
A23: =IF(D23<>"",ROW()-3,"") | N23: =IF(L23<>"",L23+IF(M23<>"",M23,0),"") | S23: =IF(Q23<>"",Q23-IF(N23<>"",N23,0),"")
A24: =IF(D24<>"",ROW()-3,"") | N24: =IF(L24<>"",L24+IF(M24<>"",M24,0),"") | S24: =IF(Q24<>"",Q24-IF(N24<>"",N24,0),"")
A25: =IF(D25<>"",ROW()-3,"") | N25: =IF(L25<>"",L25+IF(M25<>"",M25,0),"") | S25: =IF(Q25<>"",Q25-IF(N25<>"",N25,0),"")
A26: =IF(D26<>"",ROW()-3,"") | N26: =IF(L26<>"",L26+IF(M26<>"",M26,0),"") | S26: =IF(Q26<>"",Q26-IF(N26<>"",N26,0),"")
A27: =IF(D27<>"",ROW()-3,"") | N27: =IF(L27<>"",L27+IF(M27<>"",M27,0),"") | S27: =IF(Q27<>"",Q27-IF(N27<>"",N27,0),"")
A28: =IF(D28<>"",ROW()-3,"") | N28: =IF(L28<>"",L28+IF(M28<>"",M28,0),"") | S28: =IF(Q28<>"",Q28-IF(N28<>"",N28,0),"")
A29: =IF(D29<>"",ROW()-3,"") | N29: =IF(L29<>"",L29+IF(M29<>"",M29,0),"") | S29: =IF(Q29<>"",Q29-IF(N29<>"",N29,0),"")
A30: =IF(D30<>"",ROW()-3,"") | N30: =IF(L30<>"",L30+IF(M30<>"",M30,0),"") | S30: =IF(Q30<>"",Q30-IF(N30<>"",N30,0),"")
A31: =IF(D31<>"",ROW()-3,"") | N31: =IF(L31<>"",L31+IF(M31<>"",M31,0),"") | S31: =IF(Q31<>"",Q31-IF(N31<>"",N31,0),"")
A32: =IF(D32<>"",ROW()-3,"") | N32: =IF(L32<>"",L32+IF(M32<>"",M32,0),"") | S32: =IF(Q32<>"",Q32-IF(N32<>"",N32,0),"")
A33: =IF(D33<>"",ROW()-3,"") | N33: =IF(L33<>"",L33+IF(M33<>"",M33,0),"") | S33: =IF(Q33<>"",Q33-IF(N33<>"",N33,0),"")
A34: =IF(D34<>"",ROW()-3,"") | N34: =IF(L34<>"",L34+IF(M34<>"",M34,0),"") | S34: =IF(Q34<>"",Q34-IF(N34<>"",N34,0),"")
... A103: =IF(D103<>"",ROW()-3,"") | N103: =IF(L103<>"",L103+IF(M103<>"",M103,0),"") | S103: =IF(Q103<>"",Q103-IF(N103<>"",N103,0),"")

Sheet 💰 Capital
A1: 💰 CONTROL DE CAPITAL
A2: El saldo se actualiza automáticamente con cada compra y venta registrada en 📦 Registro.
B4: ✏️ Capital inicial (ingrésalo tú)
B5: 200000
B6: ↑ Escribe aquí tu capital disponible actual en CLP
B8: 💸 Total Invertido (compras)
B9: =IFERROR(SUM('📦 Registro'!N4:N103),0) -> 3654000
B11: ✅ Total Recaudado (ventas)
B12: =IFERROR(SUM('📦 Registro'!Q4:Q103),0) -> 2011000
B14: 📦 Capital en Stock (sin vender)
B15: =IFERROR(SUMPRODUCT(('📦 Registro'!O4:O103="")*('📦 Registro'!N4:N103)),0) -> 2210000
B18: 💵 SALDO DISPONIBLE
B19: =B5+B12-B9 -> -1443000
B20: Capital inicial + Ventas cobradas - Compras realizadas
B22: 📋 HISTORIAL DE MOVIMIENTOS (primeras 15 entradas del Registro)
B23: Fecha Compra | C23: Equipo | D23: Tipo | E23: Monto (CLP) | F23: Saldo Acum.
B24: ='📦 Registro'!C4 -> 46165 | C24: ='📦 Registro'!D4 -> HUAWEI NOVA 14 PRO | D24: =IF('📦 Registro'!O4<>"","Venta",IF('📦 Registro'!L4<>"","Compra","")) -> Venta | E24: =IF('📦 Registro'!O4<>"",'📦 Registro'!Q4,IF('📦 Registro'!L4<>"",-'📦 Registro'!N4,"")) -> 230000 | F24: =IF(E24<>"",B5+E24,"") -> 430000
B25: ='📦 Registro'!C5 -> 46161 | C25: ='📦 Registro'!D5 -> REDMI NOTE 13 PRO PLUS - IMEI 2 - TAPA TRIZADA | D25: =IF('📦 Registro'!O5<>"","Venta",IF('📦 Registro'!L5<>"","Compra","")) -> Venta | E25: =IF('📦 Registro'!O5<>"",'📦 Registro'!Q5,IF('📦 Registro'!L5<>"",-'📦 Registro'!N5,"")) -> 100000 | F25: =IF(E25<>"",F24+E25,"") -> 530000
B26: ='📦 Registro'!C6 -> 46161 | C26: ='📦 Registro'!D6 -> SAMSUNG GALAXY A55 8/128 | D26: =IF('📦 Registro'!O6<>"","Venta",IF('📦 Registro'!L6<>"","Compra","")) -> Venta | E26: =IF('📦 Registro'!O6<>"",'📦 Registro'!Q6,IF('📦 Registro'!L6<>"",-'📦 Registro'!N6,"")) -> 70000 | F26: =IF(E26<>"",F25+E26,"") -> 600000
B27: ='📦 Registro'!C7 -> 46170 | C27: ='📦 Registro'!D7 -> APPLE IPHONE 14 PRO 256GB | D27: =IF('📦 Registro'!O7<>"","Venta",IF('📦 Registro'!L7<>"","Compra","")) -> Venta | E27: =IF('📦 Registro'!O7<>"",'📦 Registro'!Q7,IF('📦 Registro'!L7<>"",-'📦 Registro'!N7,"")) -> 370000 | F27: =IF(E27<>"",F26+E27,"") -> 970000
B28: ='📦 Registro'!C8 -> 46170 | C28: ='📦 Registro'!D8 -> APPLE IPHONE 11 PRO 64GB | D28: =IF('📦 Registro'!O8<>"","Venta",IF('📦 Registro'!L8<>"","Compra","")) -> Compra | E28: =IF('📦 Registro'!O8<>"",'📦 Registro'!Q8,IF('📦 Registro'!L8<>"",-'📦 Registro'!N8,"")) -> -20000 | F28: =IF(E28<>"",F27+E28,"") -> 950000
B29: ='📦 Registro'!C9 -> 46170 | C29: ='📦 Registro'!D9 -> HONOR POWER 2 12/256 | D29: =IF('📦 Registro'!O9<>"","Venta",IF('📦 Registro'!L9<>"","Compra","")) -> Venta | E29: =IF('📦 Registro'!O9<>"",'📦 Registro'!Q9,IF('📦 Registro'!L9<>"",-'📦 Registro'!N9,"")) -> 150000 | F29: =IF(E29<>"",F28+E29,"") -> 1100000
B30: ='📦 Registro'!C10 -> 46125 | C30: ='📦 Registro'!D10 -> ASUS PROART STUDIOBOOK I9/64 GB | D30: =IF('📦 Registro'!O10<>"","Venta",IF('📦 Registro'!L10<>"","Compra","")) -> Compra | E30: =IF('📦 Registro'!O10<>"",'📦 Registro'!Q10,IF('📦 Registro'!L10<>"",-'📦 Registro'!N10,"")) -> -850000 | F30: =IF(E30<>"",F29+E30,"") -> 250000
B31: ='📦 Registro'!C11 -> 46182 | C31: ='📦 Registro'!D11 -> LENOVO THINKBOOK P16 GEN 2 | D31: =IF('📦 Registro'!O11<>"","Venta",IF('📦 Registro'!L11<>"","Compra","")) -> Compra | E31: =IF('📦 Registro'!O11<>"",'📦 Registro'!Q11,IF('📦 Registro'!L11<>"",-'📦 Registro'!N11,"")) -> -480000 | F31: =IF(E31<>"",F30+E31,"") -> -230000
B32: ='📦 Registro'!C12 -> 46183 | C32: ='📦 Registro'!D12 -> LENOVO LEGION 5 I7/32GB/1TB | D32: =IF('📦 Registro'!O12<>"","Venta",IF('📦 Registro'!L12<>"","Compra","")) -> Venta | E32: =IF('📦 Registro'!O12<>"",'📦 Registro'!Q12,IF('📦 Registro'!L12<>"",-'📦 Registro'!N12,"")) -> 300000 | F32: =IF(E32<>"",F31+E32,"") -> 70000
B33: ='📦 Registro'!C13 -> 46181 | C33: ='📦 Registro'!D13 -> DELL VOSTRO 3405 RYZEN 5 | D33: =IF('📦 Registro'!O13<>"","Venta",IF('📦 Registro'!L13<>"","Compra","")) -> Compra | E33: =IF('📦 Registro'!O13<>"",'📦 Registro'!Q13,IF('📦 Registro'!L13<>"",-'📦 Registro'!N13,"")) -> -50000 | F33: =IF(E33<>"",F32+E33,"") -> 20000
B34: ='📦 Registro'!C14 -> 46170 | C34: ='📦 Registro'!D14 -> APPLE WATCH SE GEN 2 44M + CELLULAR | D34: =IF('📦 Registro'!O14<>"","Venta",IF('📦 Registro'!L14<>"","Compra","")) -> Compra | E34: =IF('📦 Registro'!O14<>"",'📦 Registro'!Q14,IF('📦 Registro'!L14<>"",-'📦 Registro'!N14,"")) -> -50000 | F34: =IF(E34<>"",F33+E34,"") -> -30000
B35: ='📦 Registro'!C15 -> 46147 | C35: ='📦 Registro'!D15 -> LENOVO THINKCENTRE M70Q GEN 6 | D35: =IF('📦 Registro'!O15<>"","Venta",IF('📦 Registro'!L15<>"","Compra","")) -> Compra | E35: =IF('📦 Registro'!O15<>"",'📦 Registro'!Q15,IF('📦 Registro'!L15<>"",-'📦 Registro'!N15,"")) -> -300000 | F35: =IF(E35<>"",F34+E35,"") -> -330000
B36: ='📦 Registro'!C16 -> 46101 | C36: ='📦 Registro'!D16 -> TORRE THREADRIPPER | D36: =IF('📦 Registro'!O16<>"","Venta",IF('📦 Registro'!L16<>"","Compra","")) -> Compra | E36: =IF('📦 Registro'!O16<>"",'📦 Registro'!Q16,IF('📦 Registro'!L16<>"",-'📦 Registro'!N16,"")) -> -320000 | F36: =IF(E36<>"",F35+E36,"") -> -650000
... B38: ='📦 Registro'!C18 -> 46190 | C38: ='📦 Registro'!D18 -> REDMI NOTE 15 PRO 512GB | D38: =IF('📦 Registro'!O18<>"","Venta",IF('📦 Registro'!L18<>"","Compra","")) -> Venta | E38: =IF('📦 Registro'!O18<>"",'📦 Registro'!Q18,IF('📦 Registro'!L18<>"",-'📦 Registro'!N18,"")) -> 150000 | F38: =IF(E38<>"",F37+E38,"") -> -139000

Sheet 📋 Stock Activo
A1: 📋 STOCK ACTIVO — Equipos disponibles para vender
A2: Se actualiza automáticamente. Solo aparecen equipos SIN fecha de venta.
A3: ID | B3: Categoría | C3: Equipo | D3: Marca | E3: Estado | F3: Fecha Compra | G3: Costo Total | H3: Días en Stock
B4: {=IFERROR(IF(I4="","",INDEX('📦 Registro'!$B$4:$B$103,MATCH(I4,'📦 Registro'!$A$4:$A$103,0))),"")} | C4: {=IFERROR(IF(I4="","",INDEX('📦 Registro'!$D$4:$D$103,MATCH(I4,'📦 Registro'!$A$4:$A$103,0))),"")} | D4: {=IFERROR(IF(I4="","",INDEX('📦 Registro'!$E$4:$E$103,MATCH(I4,'📦 Registro'!$A$4:$A$103,0))),"")} | E4: {=IFERROR(IF(I4="","",INDEX('📦 Registro'!$I$4:$I$103,MATCH(I4,'📦 Registro'!$A$4:$A$103,0))),"")} | F4: {=IFERROR(IF(I4="","",INDEX('📦 Registro'!$C$4:$C$103,MATCH(I4,'📦 Registro'!$A$4:$A$103,0))),"")} | G4: {=IFERROR(IF(I4="","",INDEX('📦 Registro'!$N$4:$N$103,MATCH(I4,'📦 Registro'!$A$4:$A$103,0))),"")} | H4: =IFERROR(IF(F4="","",TODAY()-F4),"") | I4: {=IFERROR(INDEX(#REF!,MATCH(SMALL(IF(#REF!<>"",ROW(#REF!)-3),1),#REF!,0)),"")}
A5: {=IFERROR(IF(I5="","",INDEX('📦 Registro'!$A$4:$A$103,MATCH(I5,'📦 Registro'!$A$4:$A$103,0))),"")} | B5: {=IFERROR(IF(I5="","",INDEX('📦 Registro'!$B$4:$B$103,MATCH(I5,'📦 Registro'!$A$4:$A$103,0))),"")} | C5: {=IFERROR(IF(I5="","",INDEX('📦 Registro'!$D$4:$D$103,MATCH(I5,'📦 Registro'!$A$4:$A$103,0))),"")} | D5: {=IFERROR(IF(I5="","",INDEX('📦 Registro'!$E$4:$E$103,MATCH(I5,'📦 Registro'!$A$4:$A$103,0))),"")} | E5: {=IFERROR(IF(I5="","",INDEX('📦 Registro'!$I$4:$I$103,MATCH(I5,'📦 Registro'!$A$4:$A$103,0))),"")} | F5: {=IFERROR(IF(I5="","",INDEX('📦 Registro'!$C$4:$C$103,MATCH(I5,'📦 Registro'!$A$4:$A$103,0))),"")} | G5: {=IFERROR(IF(I5="","",INDEX('📦 Registro'!$N$4:$N$103,MATCH(I5,'📦 Registro'!$A$4:$A$103,0))),"")} | H5: =IFERROR(IF(F5="","",TODAY()-F5),"") | I5: {=IFERROR(INDEX(#REF!,MATCH(SMALL(IF(#REF!<>"",ROW(#REF!)-3),2),#REF!,0)),"")}
A6: {=IFERROR(IF(I6="","",INDEX('📦 Registro'!$A$4:$A$103,MATCH(I6,'📦 Registro'!$A$4:$A$103,0))),"")} | B6: {=IFERROR(IF(I6="","",INDEX('📦 Registro'!$B$4:$B$103,MATCH(I6,'📦 Registro'!$A$4:$A$103,0))),"")} | C6: {=IFERROR(IF(I6="","",INDEX('📦 Registro'!$D$4:$D$103,MATCH(I6,'📦 Registro'!$A$4:$A$103,0))),"")} | D6: {=IFERROR(IF(I6="","",INDEX('📦 Registro'!$E$4:$E$103,MATCH(I6,'📦 Registro'!$A$4:$A$103,0))),"")} | E6: {=IFERROR(IF(I6="","",INDEX('📦 Registro'!$I$4:$I$103,MATCH(I6,'📦 Registro'!$A$4:$A$103,0))),"")} | F6: {=IFERROR(IF(I6="","",INDEX('📦 Registro'!$C$4:$C$103,MATCH(I6,'📦 Registro'!$A$4:$A$103,0))),"")} | G6: {=IFERROR(IF(I6="","",INDEX('📦 Registro'!$N$4:$N$103,MATCH(I6,'📦 Registro'!$A$4:$A$103,0))),"")} | H6: =IFERROR(IF(F6="","",TODAY()-F6),"") | I6: {=IFERROR(INDEX(#REF!,MATCH(SMALL(IF(#REF!<>"",ROW(#REF!)-3),3),#REF!,0)),"")}
A7: {=IFERROR(IF(I7="","",INDEX('📦 Registro'!$A$4:$A$103,MATCH(I7,'📦 Registro'!$A$4:$A$103,0))),"")} | B7: {=IFERROR(IF(I7="","",INDEX('📦 Registro'!$B$4:$B$103,MATCH(I7,'📦 Registro'!$A$4:$A$103,0))),"")} | C7: {=IFERROR(IF(I7="","",INDEX('📦 Registro'!$D$4:$D$103,MATCH(I7,'📦 Registro'!$A$4:$A$103,0))),"")} | D7: {=IFERROR(IF(I7="","",INDEX('📦 Registro'!$E$4:$E$103,MATCH(I7,'📦 Registro'!$A$4:$A$103,0))),"")} | E7: {=IFERROR(IF(I7="","",INDEX('📦 Registro'!$I$4:$I$103,MATCH(I7,'📦 Registro'!$A$4:$A$103,0))),"")} | F7: {=IFERROR(IF(I7="","",INDEX('📦 Registro'!$C$4:$C$103,MATCH(I7,'📦 Registro'!$A$4:$A$103,0))),"")} | G7: {=IFERROR(IF(I7="","",INDEX('📦 Registro'!$N$4:$N$103,MATCH(I7,'📦 Registro'!$A$4:$A$103,0))),"")} | H7: =IFERROR(IF(F7="","",TODAY()-F7),"") | I7: {=IFERROR(INDEX(#REF!,MATCH(SMALL(IF(#REF!<>"",ROW(#REF!)-3),4),#REF!,0)),"")}
A8: {=IFERROR(IF(I8="","",INDEX('📦 Registro'!$A$4:$A$103,MATCH(I8,'📦 Registro'!$A$4:$A$103,0))),"")} | B8: {=IFERROR(IF(I8="","",INDEX('📦 Registro'!$B$4:$B$103,MATCH(I8,'📦 Registro'!$A$4:$A$103,0))),"")} | C8: {=IFERROR(IF(I8="","",INDEX('📦 Registro'!$D$4:$D$103,MATCH(I8,'📦 Registro'!$A$4:$A$103,0))),"")} | D8: {=IFERROR(IF(I8="","",INDEX('📦 Registro'!$E$4:$E$103,MATCH(I8,'📦 Registro'!$A$4:$A$103,0))),"")} | E8: {=IFERROR(IF(I8="","",INDEX('📦 Registro'!$I$4:$I$103,MATCH(I8,'📦 Registro'!$A$4:$A$103,0))),"")} | F8: {=IFERROR(IF(I8="","",INDEX('📦 Registro'!$C$4:$C$103,MATCH(I8,'📦 Registro'!$A$4:$A$103,0))),"")} | G8: {=IFERROR(IF(I8="","",INDEX('📦 Registro'!$N$4:$N$103,MATCH(I8,'📦 Registro'!$A$4:$A$103,0))),"")} | H8: =IFERROR(IF(F8="","",TODAY()-F8),"") | I8: {=IFERROR(INDEX(#REF!,MATCH(SMALL(IF(#REF!<>"",ROW(#REF!)-3),5),#REF!,0)),"")}
A9: {=IFERROR(IF(I9="","",INDEX('📦 Registro'!$A$4:$A$103,MATCH(I9,'📦 Registro'!$A$4:$A$103,0))),"")} | B9: {=IFERROR(IF(I9="","",INDEX('📦 Registro'!$B$4:$B$103,MATCH(I9,'📦 Registro'!$A$4:$A$103,0))),"")} | C9: {=IFERROR(IF(I9="","",INDEX('📦 Registro'!$D$4:$D$103,MATCH(I9,'📦 Registro'!$A$4:$A$103,0))),"")} | D9: {=IFERROR(IF(I9="","",INDEX('📦 Registro'!$E$4:$E$103,MATCH(I9,'📦 Registro'!$A$4:$A$103,0))),"")} | E9: {=IFERROR(IF(I9="","",INDEX('📦 Registro'!$I$4:$I$103,MATCH(I9,'📦 Registro'!$A$4:$A$103,0))),"")} | F9: {=IFERROR(IF(I9="","",INDEX('📦 Registro'!$C$4:$C$103,MATCH(I9,'📦 Registro'!$A$4:$A$103,0))),"")} | G9: {=IFERROR(IF(I9="","",INDEX('📦 Registro'!$N$4:$N$103,MATCH(I9,'📦 Registro'!$A$4:$A$103,0))),"")} | H9: =IFERROR(IF(F9="","",TODAY()-F9),"") | I9: {=IFERROR(INDEX(#REF!,MATCH(SMALL(IF(#REF!<>"",ROW(#REF!)-3),6),#REF!,0)),"")}
A10: {=IFERROR(IF(I10="","",INDEX('📦 Registro'!$A$4:$A$103,MATCH(I10,'📦 Registro'!$A$4:$A$103,0))),"")} | B10: {=IFERROR(IF(I10="","",INDEX('📦 Registro'!$B$4:$B$103,MATCH(I10,'📦 Registro'!$A$4:$A$103,0))),"")} | C10: {=IFERROR(IF(I10="","",INDEX('📦 Registro'!$D$4:$D$103,MATCH(I10,'📦 Registro'!$A$4:$A$103,0))),"")} | D10: {=IFERROR(IF(I10="","",INDEX('📦 Registro'!$E$4:$E$103,MATCH(I10,'📦 Registro'!$A$4:$A$103,0))),"")} | E10: {=IFERROR(IF(I10="","",INDEX('📦 Registro'!$I$4:$I$103,MATCH(I10,'📦 Registro'!$A$4:$A$103,0))),"")} | F10: {=IFERROR(IF(I10="","",INDEX('📦 Registro'!$C$4:$C$103,MATCH(I10,'📦 Registro'!$A$4:$A$103,0))),"")} | G10: {=IFERROR(IF(I10="","",INDEX('📦 Registro'!$N$4:$N$103,MATCH(I10,'📦 Registro'!$A$4:$A$103,0))),"")} | H10: =IFERROR(IF(F10="","",TODAY()-F10),"") | I10: {=IFERROR(INDEX(#REF!,MATCH(SMALL(IF(#REF!<>"",ROW(#REF!)-3),7),#REF!,0)),"")}
A11: {=IFERROR(IF(I11="","",INDEX('📦 Registro'!$A$4:$A$103,MATCH(I11,'📦 Registro'!$A$4:$A$103,0))),"")} | B11: {=IFERROR(IF(I11="","",INDEX('📦 Registro'!$B$4:$B$103,MATCH(I11,'📦 Registro'!$A$4:$A$103,0))),"")} | C11: {=IFERROR(IF(I11="","",INDEX('📦 Registro'!$D$4:$D$103,MATCH(I11,'📦 Registro'!$A$4:$A$103,0))),"")} | D11: {=IFERROR(IF(I11="","",INDEX('📦 Registro'!$E$4:$E$103,MATCH(I11,'📦 Registro'!$A$4:$A$103,0))),"")} | E11: {=IFERROR(IF(I11="","",INDEX('📦 Registro'!$I$4:$I$103,MATCH(I11,'📦 Registro'!$A$4:$A$103,0))),"")} | F11: {=IFERROR(IF(I11="","",INDEX('📦 Registro'!$C$4:$C$103,MATCH(I11,'📦 Registro'!$A$4:$A$103,0))),"")} | G11: {=IFERROR(IF(I11="","",INDEX('📦 Registro'!$N$4:$N$103,MATCH(I11,'📦 Registro'!$A$4:$A$103,0))),"")} | H11: =IFERROR(IF(F11="","",TODAY()-F11),"") | I11: {=IFERROR(INDEX(#REF!,MATCH(SMALL(IF(#REF!<>"",ROW(#REF!)-3),8),#REF!,0)),"")}
A12: {=IFERROR(IF(I12="","",INDEX('📦 Registro'!$A$4:$A$103,MATCH(I12,'📦 Registro'!$A$4:$A$103,0))),"")} | B12: {=IFERROR(IF(I12="","",INDEX('📦 Registro'!$B$4:$B$103,MATCH(I12,'📦 Registro'!$A$4:$A$103,0))),"")} | C12: {=IFERROR(IF(I12="","",INDEX('📦 Registro'!$D$4:$D$103,MATCH(I12,'📦 Registro'!$A$4:$A$103,0))),"")} | D12: {=IFERROR(IF(I12="","",INDEX('📦 Registro'!$E$4:$E$103,MATCH(I12,'📦 Registro'!$A$4:$A$103,0))),"")} | E12: {=IFERROR(IF(I12="","",INDEX('📦 Registro'!$I$4:$I$103,MATCH(I12,'📦 Registro'!$A$4:$A$103,0))),"")} | F12: {=IFERROR(IF(I12="","",INDEX('📦 Registro'!$C$4:$C$103,MATCH(I12,'📦 Registro'!$A$4:$A$103,0))),"")} | G12: {=IFERROR(IF(I12="","",INDEX('📦 Registro'!$N$4:$N$103,MATCH(I12,'📦 Registro'!$A$4:$A$103,0))),"")} | H12: =IFERROR(IF(F12="","",TODAY()-F12),"") | I12: {=IFERROR(INDEX(#REF!,MATCH(SMALL(IF(#REF!<>"",ROW(#REF!)-3),9),#REF!,0)),"")}
A13: {=IFERROR(IF(I13="","",INDEX('📦 Registro'!$A$4:$A$103,MATCH(I13,'📦 Registro'!$A$4:$A$103,0))),"")} | B13: {=IFERROR(IF(I13="","",INDEX('📦 Registro'!$B$4:$B$103,MATCH(I13,'📦 Registro'!$A$4:$A$103,0))),"")} | C13: {=IFERROR(IF(I13="","",INDEX('📦 Registro'!$D$4:$D$103,MATCH(I13,'📦 Registro'!$A$4:$A$103,0))),"")} | D13: {=IFERROR(IF(I13="","",INDEX('📦 Registro'!$E$4:$E$103,MATCH(I13,'📦 Registro'!$A$4:$A$103,0))),"")} | E13: {=IFERROR(IF(I13="","",INDEX('📦 Registro'!$I$4:$I$103,MATCH(I13,'📦 Registro'!$A$4:$A$103,0))),"")} | F13: {=IFERROR(IF(I13="","",INDEX('📦 Registro'!$C$4:$C$103,MATCH(I13,'📦 Registro'!$A$4:$A$103,0))),"")} | G13: {=IFERROR(IF(I13="","",INDEX('📦 Registro'!$N$4:$N$103,MATCH(I13,'📦 Registro'!$A$4:$A$103,0))),"")} | H13: =IFERROR(IF(F13="","",TODAY()-F13),"") | I13: {=IFERROR(INDEX(#REF!,MATCH(SMALL(IF(#REF!<>"",ROW(#REF!)-3),10),#REF!,0)),"")}
A14: {=IFERROR(IF(I14="","",INDEX('📦 Registro'!$A$4:$A$103,MATCH(I14,'📦 Registro'!$A$4:$A$103,0))),"")} | B14: {=IFERROR(IF(I14="","",INDEX('📦 Registro'!$B$4:$B$103,MATCH(I14,'📦 Registro'!$A$4:$A$103,0))),"")} | C14: {=IFERROR(IF(I14="","",INDEX('📦 Registro'!$D$4:$D$103,MATCH(I14,'📦 Registro'!$A$4:$A$103,0))),"")} | D14: {=IFERROR(IF(I14="","",INDEX('📦 Registro'!$E$4:$E$103,MATCH(I14,'📦 Registro'!$A$4:$A$103,0))),"")} | E14: {=IFERROR(IF(I14="","",INDEX('📦 Registro'!$I$4:$I$103,MATCH(I14,'📦 Registro'!$A$4:$A$103,0))),"")} | F14: {=IFERROR(IF(I14="","",INDEX('📦 Registro'!$C$4:$C$103,MATCH(I14,'📦 Registro'!$A$4:$A$103,0))),"")} | G14: {=IFERROR(IF(I14="","",INDEX('📦 Registro'!$N$4:$N$103,MATCH(I14,'📦 Registro'!$A$4:$A$103,0))),"")} | H14: =IFERROR(IF(F14="","",TODAY()-F14),"") | I14: {=IFERROR(INDEX(#REF!,MATCH(SMALL(IF(#REF!<>"",ROW(#REF!)-3),11),#REF!,0)),"")}
A15: {=IFERROR(IF(I15="","",INDEX('📦 Registro'!$A$4:$A$103,MATCH(I15,'📦 Registro'!$A$4:$A$103,0))),"")} | B15: {=IFERROR(IF(I15="","",INDEX('📦 Registro'!$B$4:$B$103,MATCH(I15,'📦 Registro'!$A$4:$A$103,0))),"")} | C15: {=IFERROR(IF(I15="","",INDEX('📦 Registro'!$D$4:$D$103,MATCH(I15,'📦 Registro'!$A$4:$A$103,0))),"")} | D15: {=IFERROR(IF(I15="","",INDEX('📦 Registro'!$E$4:$E$103,MATCH(I15,'📦 Registro'!$A$4:$A$103,0))),"")} | E15: {=IFERROR(IF(I15="","",INDEX('📦 Registro'!$I$4:$I$103,MATCH(I15,'📦 Registro'!$A$4:$A$103,0))),"")} | F15: {=IFERROR(IF(I15="","",INDEX('📦 Registro'!$C$4:$C$103,MATCH(I15,'📦 Registro'!$A$4:$A$103,0))),"")} | G15: {=IFERROR(IF(I15="","",INDEX('📦 Registro'!$N$4:$N$103,MATCH(I15,'📦 Registro'!$A$4:$A$103,0))),"")} | H15: =IFERROR(IF(F15="","",TODAY()-F15),"") | I15: {=IFERROR(INDEX(#REF!,MATCH(SMALL(IF(#REF!<>"",ROW(#REF!)-3),12),#REF!,0)),"")}
A16: {=IFERROR(IF(I16="","",INDEX('📦 Registro'!$A$4:$A$103,MATCH(I16,'📦 Registro'!$A$4:$A$103,0))),"")} | B16: {=IFERROR(IF(I16="","",INDEX('📦 Registro'!$B$4:$B$103,MATCH(I16,'📦 Registro'!$A$4:$A$103,0))),"")} | C16: {=IFERROR(IF(I16="","",INDEX('📦 Registro'!$D$4:$D$103,MATCH(I16,'📦 Registro'!$A$4:$A$103,0))),"")} | D16: {=IFERROR(IF(I16="","",INDEX('📦 Registro'!$E$4:$E$103,MATCH(I16,'📦 Registro'!$A$4:$A$103,0))),"")} | E16: {=IFERROR(IF(I16="","",INDEX('📦 Registro'!$I$4:$I$103,MATCH(I16,'📦 Registro'!$A$4:$A$103,0))),"")} | F16: {=IFERROR(IF(I16="","",INDEX('📦 Registro'!$C$4:$C$103,MATCH(I16,'📦 Registro'!$A$4:$A$103,0))),"")} | G16: {=IFERROR(IF(I16="","",INDEX('📦 Registro'!$N$4:$N$103,MATCH(I16,'📦 Registro'!$A$4:$A$103,0))),"")} | H16: =IFERROR(IF(F16="","",TODAY()-F16),"") | I16: {=IFERROR(INDEX(#REF!,MATCH(SMALL(IF(#REF!<>"",ROW(#REF!)-3),13),#REF!,0)),"")}
A17: {=IFERROR(IF(I17="","",INDEX('📦 Registro'!$A$4:$A$103,MATCH(I17,'📦 Registro'!$A$4:$A$103,0))),"")} | B17: {=IFERROR(IF(I17="","",INDEX('📦 Registro'!$B$4:$B$103,MATCH(I17,'📦 Registro'!$A$4:$A$103,0))),"")} | C17: {=IFERROR(IF(I17="","",INDEX('📦 Registro'!$D$4:$D$103,MATCH(I17,'📦 Registro'!$A$4:$A$103,0))),"")} | D17: {=IFERROR(IF(I17="","",INDEX('📦 Registro'!$E$4:$E$103,MATCH(I17,'📦 Registro'!$A$4:$A$103,0))),"")} | E17: {=IFERROR(IF(I17="","",INDEX('📦 Registro'!$I$4:$I$103,MATCH(I17,'📦 Registro'!$A$4:$A$103,0))),"")} | F17: {=IFERROR(IF(I17="","",INDEX('📦 Registro'!$C$4:$C$103,MATCH(I17,'📦 Registro'!$A$4:$A$103,0))),"")} | G17: {=IFERROR(IF(I17="","",INDEX('📦 Registro'!$N$4:$N$103,MATCH(I17,'📦 Registro'!$A$4:$A$103,0))),"")} | H17: =IFERROR(IF(F17="","",TODAY()-F17),"") | I17: {=IFERROR(INDEX(#REF!,MATCH(SMALL(IF(#REF!<>"",ROW(#REF!)-3),14),#REF!,0)),"")}
A18: {=IFERROR(IF(I18="","",INDEX('📦 Registro'!$A$4:$A$103,MATCH(I18,'📦 Registro'!$A$4:$A$103,0))),"")} | B18: {=IFERROR(IF(I18="","",INDEX('📦 Registro'!$B$4:$B$103,MATCH(I18,'📦 Registro'!$A$4:$A$103,0))),"")} | C18: {=IFERROR(IF(I18="","",INDEX('📦 Registro'!$D$4:$D$103,MATCH(I18,'📦 Registro'!$A$4:$A$103,0))),"")} | D18: {=IFERROR(IF(I18="","",INDEX('📦 Registro'!$E$4:$E$103,MATCH(I18,'📦 Registro'!$A$4:$A$103,0))),"")} | E18: {=IFERROR(IF(I18="","",INDEX('📦 Registro'!$I$4:$I$103,MATCH(I18,'📦 Registro'!$A$4:$A$103,0))),"")} | F18: {=IFERROR(IF(I18="","",INDEX('📦 Registro'!$C$4:$C$103,MATCH(I18,'📦 Registro'!$A$4:$A$103,0))),"")} | G18: {=IFERROR(IF(I18="","",INDEX('📦 Registro'!$N$4:$N$103,MATCH(I18,'📦 Registro'!$A$4:$A$103,0))),"")} | H18: =IFERROR(IF(F18="","",TODAY()-F18),"") | I18: {=IFERROR(INDEX(#REF!,MATCH(SMALL(IF(#REF!<>"",ROW(#REF!)-3),15),#REF!,0)),"")}
A19: {=IFERROR(IF(I19="","",INDEX('📦 Registro'!$A$4:$A$103,MATCH(I19,'📦 Registro'!$A$4:$A$103,0))),"")} | B19: {=IFERROR(IF(I19="","",INDEX('📦 Registro'!$B$4:$B$103,MATCH(I19,'📦 Registro'!$A$4:$A$103,0))),"")} | C19: {=IFERROR(IF(I19="","",INDEX('📦 Registro'!$D$4:$D$103,MATCH(I19,'📦 Registro'!$A$4:$A$103,0))),"")} | D19: {=IFERROR(IF(I19="","",INDEX('📦 Registro'!$E$4:$E$103,MATCH(I19,'📦 Registro'!$A$4:$A$103,0))),"")} | E19: {=IFERROR(IF(I19="","",INDEX('📦 Registro'!$I$4:$I$103,MATCH(I19,'📦 Registro'!$A$4:$A$103,0))),"")} | F19: {=IFERROR(IF(I19="","",INDEX('📦 Registro'!$C$4:$C$103,MATCH(I19,'📦 Registro'!$A$4:$A$103,0))),"")} | G19: {=IFERROR(IF(I19="","",INDEX('📦 Registro'!$N$4:$N$103,MATCH(I19,'📦 Registro'!$A$4:$A$103,0))),"")} | H19: =IFERROR(IF(F19="","",TODAY()-F19),"") | I19: {=IFERROR(INDEX(#REF!,MATCH(SMALL(IF(#REF!<>"",ROW(#REF!)-3),16),#REF!,0)),"")}
A20: {=IFERROR(IF(I20="","",INDEX('📦 Registro'!$A$4:$A$103,MATCH(I20,'📦 Registro'!$A$4:$A$103,0))),"")} | B20: {=IFERROR(IF(I20="","",INDEX('📦 Registro'!$B$4:$B$103,MATCH(I20,'📦 Registro'!$A$4:$A$103,0))),"")} | C20: {=IFERROR(IF(I20="","",INDEX('📦 Registro'!$D$4:$D$103,MATCH(I20,'📦 Registro'!$A$4:$A$103,0))),"")} | D20: {=IFERROR(IF(I20="","",INDEX('📦 Registro'!$E$4:$E$103,MATCH(I20,'📦 Registro'!$A$4:$A$103,0))),"")} | E20: {=IFERROR(IF(I20="","",INDEX('📦 Registro'!$I$4:$I$103,MATCH(I20,'📦 Registro'!$A$4:$A$103,0))),"")} | F20: {=IFERROR(IF(I20="","",INDEX('📦 Registro'!$C$4:$C$103,MATCH(I20,'📦 Registro'!$A$4:$A$103,0))),"")} | G20: {=IFERROR(IF(I20="","",INDEX('📦 Registro'!$N$4:$N$103,MATCH(I20,'📦 Registro'!$A$4:$A$103,0))),"")} | H20: =IFERROR(IF(F20="","",TODAY()-F20),"") | I20: {=IFERROR(INDEX(#REF!,MATCH(SMALL(IF(#REF!<>"",ROW(#REF!)-3),17),#REF!,0)),"")}
A21: {=IFERROR(IF(I21="","",INDEX('📦 Registro'!$A$4:$A$103,MATCH(I21,'📦 Registro'!$A$4:$A$103,0))),"")} | B21: {=IFERROR(IF(I21="","",INDEX('📦 Registro'!$B$4:$B$103,MATCH(I21,'📦 Registro'!$A$4:$A$103,0))),"")} | C21: {=IFERROR(IF(I21="","",INDEX('📦 Registro'!$D$4:$D$103,MATCH(I21,'📦 Registro'!$A$4:$A$103,0))),"")} | D21: {=IFERROR(IF(I21="","",INDEX('📦 Registro'!$E$4:$E$103,MATCH(I21,'📦 Registro'!$A$4:$A$103,0))),"")} | E21: {=IFERROR(IF(I21="","",INDEX('📦 Registro'!$I$4:$I$103,MATCH(I21,'📦 Registro'!$A$4:$A$103,0))),"")} | F21: {=IFERROR(IF(I21="","",INDEX('📦 Registro'!$C$4:$C$103,MATCH(I21,'📦 Registro'!$A$4:$A$103,0))),"")} | G21: {=IFERROR(IF(I21="","",INDEX('📦 Registro'!$N$4:$N$103,MATCH(I21,'📦 Registro'!$A$4:$A$103,0))),"")} | H21: =IFERROR(IF(F21="","",TODAY()-F21),"") | I21: {=IFERROR(INDEX(#REF!,MATCH(SMALL(IF(#REF!<>"",ROW(#REF!)-3),18),#REF!,0)),"")}
A22: {=IFERROR(IF(I22="","",INDEX('📦 Registro'!$A$4:$A$103,MATCH(I22,'📦 Registro'!$A$4:$A$103,0))),"")} | B22: {=IFERROR(IF(I22="","",INDEX('📦 Registro'!$B$4:$B$103,MATCH(I22,'📦 Registro'!$A$4:$A$103,0))),"")} | C22: {=IFERROR(IF(I22="","",INDEX('📦 Registro'!$D$4:$D$103,MATCH(I22,'📦 Registro'!$A$4:$A$103,0))),"")} | D22: {=IFERROR(IF(I22="","",INDEX('📦 Registro'!$E$4:$E$103,MATCH(I22,'📦 Registro'!$A$4:$A$103,0))),"")} | E22: {=IFERROR(IF(I22="","",INDEX('📦 Registro'!$I$4:$I$103,MATCH(I22,'📦 Registro'!$A$4:$A$103,0))),"")} | F22: {=IFERROR(IF(I22="","",INDEX('📦 Registro'!$C$4:$C$103,MATCH(I22,'📦 Registro'!$A$4:$A$103,0))),"")} | G22: {=IFERROR(IF(I22="","",INDEX('📦 Registro'!$N$4:$N$103,MATCH(I22,'📦 Registro'!$A$4:$A$103,0))),"")} | H22: =IFERROR(IF(F22="","",TODAY()-F22),"") | I22: {=IFERROR(INDEX(#REF!,MATCH(SMALL(IF(#REF!<>"",ROW(#REF!)-3),19),#REF!,0)),"")}
A23: {=IFERROR(IF(I23="","",INDEX('📦 Registro'!$A$4:$A$103,MATCH(I23,'📦 Registro'!$A$4:$A$103,0))),"")} | B23: {=IFERROR(IF(I23="","",INDEX('📦 Registro'!$B$4:$B$103,MATCH(I23,'📦 Registro'!$A$4:$A$103,0))),"")} | C23: {=IFERROR(IF(I23="","",INDEX('📦 Registro'!$D$4:$D$103,MATCH(I23,'📦 Registro'!$A$4:$A$103,0))),"")} | D23: {=IFERROR(IF(I23="","",INDEX('📦 Registro'!$E$4:$E$103,MATCH(I23,'📦 Registro'!$A$4:$A$103,0))),"")} | E23: {=IFERROR(IF(I23="","",INDEX('📦 Registro'!$I$4:$I$103,MATCH(I23,'📦 Registro'!$A$4:$A$103,0))),"")} | F23: {=IFERROR(IF(I23="","",INDEX('📦 Registro'!$C$4:$C$103,MATCH(I23,'📦 Registro'!$A$4:$A$103,0))),"")} | G23: {=IFERROR(IF(I23="","",INDEX('📦 Registro'!$N$4:$N$103,MATCH(I23,'📦 Registro'!$A$4:$A$103,0))),"")} | H23: =IFERROR(IF(F23="","",TODAY()-F23),"") | I23: {=IFERROR(INDEX(#REF!,MATCH(SMALL(IF(#REF!<>"",ROW(#REF!)-3),20),#REF!,0)),"")}
A24: {=IFERROR(IF(I24="","",INDEX('📦 Registro'!$A$4:$A$103,MATCH(I24,'📦 Registro'!$A$4:$A$103,0))),"")} | B24: {=IFERROR(IF(I24="","",INDEX('📦 Registro'!$B$4:$B$103,MATCH(I24,'📦 Registro'!$A$4:$A$103,0))),"")} | C24: {=IFERROR(IF(I24="","",INDEX('📦 Registro'!$D$4:$D$103,MATCH(I24,'📦 Registro'!$A$4:$A$103,0))),"")} | D24: {=IFERROR(IF(I24="","",INDEX('📦 Registro'!$E$4:$E$103,MATCH(I24,'📦 Registro'!$A$4:$A$103,0))),"")} | E24: {=IFERROR(IF(I24="","",INDEX('📦 Registro'!$I$4:$I$103,MATCH(I24,'📦 Registro'!$A$4:$A$103,0))),"")} | F24: {=IFERROR(IF(I24="","",INDEX('📦 Registro'!$C$4:$C$103,MATCH(I24,'📦 Registro'!$A$4:$A$103,0))),"")} | G24: {=IFERROR(IF(I24="","",INDEX('📦 Registro'!$N$4:$N$103,MATCH(I24,'📦 Registro'!$A$4:$A$103,0))),"")} | H24: =IFERROR(IF(F24="","",TODAY()-F24),"") | I24: {=IFERROR(INDEX(#REF!,MATCH(SMALL(IF(#REF!<>"",ROW(#REF!)-3),21),#REF!,0)),"")}
A25: {=IFERROR(IF(I25="","",INDEX('📦 Registro'!$A$4:$A$103,MATCH(I25,'📦 Registro'!$A$4:$A$103,0))),"")} | B25: {=IFERROR(IF(I25="","",INDEX('📦 Registro'!$B$4:$B$103,MATCH(I25,'📦 Registro'!$A$4:$A$103,0))),"")} | C25: {=IFERROR(IF(I25="","",INDEX('📦 Registro'!$D$4:$D$103,MATCH(I25,'📦 Registro'!$A$4:$A$103,0))),"")} | D25: {=IFERROR(IF(I25="","",INDEX('📦 Registro'!$E$4:$E$103,MATCH(I25,'📦 Registro'!$A$4:$A$103,0))),"")} | E25: {=IFERROR(IF(I25="","",INDEX('📦 Registro'!$I$4:$I$103,MATCH(I25,'📦 Registro'!$A$4:$A$103,0))),"")} | F25: {=IFERROR(IF(I25="","",INDEX('📦 Registro'!$C$4:$C$103,MATCH(I25,'📦 Registro'!$A$4:$A$103,0))),"")} | G25: {=IFERROR(IF(I25="","",INDEX('📦 Registro'!$N$4:$N$103,MATCH(I25,'📦 Registro'!$A$4:$A$103,0))),"")} | H25: =IFERROR(IF(F25="","",TODAY()-F25),"") | I25: {=IFERROR(INDEX(#REF!,MATCH(SMALL(IF(#REF!<>"",ROW(#REF!)-3),22),#REF!,0)),"")}
A26: {=IFERROR(IF(I26="","",INDEX('📦 Registro'!$A$4:$A$103,MATCH(I26,'📦 Registro'!$A$4:$A$103,0))),"")} | B26: {=IFERROR(IF(I26="","",INDEX('📦 Registro'!$B$4:$B$103,MATCH(I26,'📦 Registro'!$A$4:$A$103,0))),"")} | C26: {=IFERROR(IF(I26="","",INDEX('📦 Registro'!$D$4:$D$103,MATCH(I26,'📦 Registro'!$A$4:$A$103,0))),"")} | D26: {=IFERROR(IF(I26="","",INDEX('📦 Registro'!$E$4:$E$103,MATCH(I26,'📦 Registro'!$A$4:$A$103,0))),"")} | E26: {=IFERROR(IF(I26="","",INDEX('📦 Registro'!$I$4:$I$103,MATCH(I26,'📦 Registro'!$A$4:$A$103,0))),"")} | F26: {=IFERROR(IF(I26="","",INDEX('📦 Registro'!$C$4:$C$103,MATCH(I26,'📦 Registro'!$A$4:$A$103,0))),"")} | G26: {=IFERROR(IF(I26="","",INDEX('📦 Registro'!$N$4:$N$103,MATCH(I26,'📦 Registro'!$A$4:$A$103,0))),"")} | H26: =IFERROR(IF(F26="","",TODAY()-F26),"") | I26: {=IFERROR(INDEX(#REF!,MATCH(SMALL(IF(#REF!<>"",ROW(#REF!)-3),23),#REF!,0)),"")}
A27: {=IFERROR(IF(I27="","",INDEX('📦 Registro'!$A$4:$A$103,MATCH(I27,'📦 Registro'!$A$4:$A$103,0))),"")} | B27: {=IFERROR(IF(I27="","",INDEX('📦 Registro'!$B$4:$B$103,MATCH(I27,'📦 Registro'!$A$4:$A$103,0))),"")} | C27: {=IFERROR(IF(I27="","",INDEX('📦 Registro'!$D$4:$D$103,MATCH(I27,'📦 Registro'!$A$4:$A$103,0))),"")} | D27: {=IFERROR(IF(I27="","",INDEX('📦 Registro'!$E$4:$E$103,MATCH(I27,'📦 Registro'!$A$4:$A$103,0))),"")} | E27: {=IFERROR(IF(I27="","",INDEX('📦 Registro'!$I$4:$I$103,MATCH(I27,'📦 Registro'!$A$4:$A$103,0))),"")} | F27: {=IFERROR(IF(I27="","",INDEX('📦 Registro'!$C$4:$C$103,MATCH(I27,'📦 Registro'!$A$4:$A$103,0))),"")} | G27: {=IFERROR(IF(I27="","",INDEX('📦 Registro'!$N$4:$N$103,MATCH(I27,'📦 Registro'!$A$4:$A$103,0))),"")} | H27: =IFERROR(IF(F27="","",TODAY()-F27),"") | I27: {=IFERROR(INDEX(#REF!,MATCH(SMALL(IF(#REF!<>"",ROW(#REF!)-3),24),#REF!,0)),"")}
A28: {=IFERROR(IF(I28="","",INDEX('📦 Registro'!$A$4:$A$103,MATCH(I28,'📦 Registro'!$A$4:$A$103,0))),"")} | B28: {=IFERROR(IF(I28="","",INDEX('📦 Registro'!$B$4:$B$103,MATCH(I28,'📦 Registro'!$A$4:$A$103,0))),"")} | C28: {=IFERROR(IF(I28="","",INDEX('📦 Registro'!$D$4:$D$103,MATCH(I28,'📦 Registro'!$A$4:$A$103,0))),"")} | D28: {=IFERROR(IF(I28="","",INDEX('📦 Registro'!$E$4:$E$103,MATCH(I28,'📦 Registro'!$A$4:$A$103,0))),"")} | E28: {=IFERROR(IF(I28="","",INDEX('📦 Registro'!$I$4:$I$103,MATCH(I28,'📦 Registro'!$A$4:$A$103,0))),"")} | F28: {=IFERROR(IF(I28="","",INDEX('📦 Registro'!$C$4:$C$103,MATCH(I28,'📦 Registro'!$A$4:$A$103,0))),"")} | G28: {=IFERROR(IF(I28="","",INDEX('📦 Registro'!$N$4:$N$103,MATCH(I28,'📦 Registro'!$A$4:$A$103,0))),"")} | H28: =IFERROR(IF(F28="","",TODAY()-F28),"") | I28: {=IFERROR(INDEX(#REF!,MATCH(SMALL(IF(#REF!<>"",ROW(#REF!)-3),25),#REF!,0)),"")}
A29: {=IFERROR(IF(I29="","",INDEX('📦 Registro'!$A$4:$A$103,MATCH(I29,'📦 Registro'!$A$4:$A$103,0))),"")} | B29: {=IFERROR(IF(I29="","",INDEX('📦 Registro'!$B$4:$B$103,MATCH(I29,'📦 Registro'!$A$4:$A$103,0))),"")} | C29: {=IFERROR(IF(I29="","",INDEX('📦 Registro'!$D$4:$D$103,MATCH(I29,'📦 Registro'!$A$4:$A$103,0))),"")} | D29: {=IFERROR(IF(I29="","",INDEX('📦 Registro'!$E$4:$E$103,MATCH(I29,'📦 Registro'!$A$4:$A$103,0))),"")} | E29: {=IFERROR(IF(I29="","",INDEX('📦 Registro'!$I$4:$I$103,MATCH(I29,'📦 Registro'!$A$4:$A$103,0))),"")} | F29: {=IFERROR(IF(I29="","",INDEX('📦 Registro'!$C$4:$C$103,MATCH(I29,'📦 Registro'!$A$4:$A$103,0))),"")} | G29: {=IFERROR(IF(I29="","",INDEX('📦 Registro'!$N$4:$N$103,MATCH(I29,'📦 Registro'!$A$4:$A$103,0))),"")} | H29: =IFERROR(IF(F29="","",TODAY()-F29),"") | I29: {=IFERROR(INDEX(#REF!,MATCH(SMALL(IF(#REF!<>"",ROW(#REF!)-3),26),#REF!,0)),"")}
A30: {=IFERROR(IF(I30="","",INDEX('📦 Registro'!$A$4:$A$103,MATCH(I30,'📦 Registro'!$A$4:$A$103,0))),"")} | B30: {=IFERROR(IF(I30="","",INDEX('📦 Registro'!$B$4:$B$103,MATCH(I30,'📦 Registro'!$A$4:$A$103,0))),"")} | C30: {=IFERROR(IF(I30="","",INDEX('📦 Registro'!$D$4:$D$103,MATCH(I30,'📦 Registro'!$A$4:$A$103,0))),"")} | D30: {=IFERROR(IF(I30="","",INDEX('📦 Registro'!$E$4:$E$103,MATCH(I30,'📦 Registro'!$A$4:$A$103,0))),"")} | E30: {=IFERROR(IF(I30="","",INDEX('📦 Registro'!$I$4:$I$103,MATCH(I30,'📦 Registro'!$A$4:$A$103,0))),"")} | F30: {=IFERROR(IF(I30="","",INDEX('📦 Registro'!$C$4:$C$103,MATCH(I30,'📦 Registro'!$A$4:$A$103,0))),"")} | G30: {=IFERROR(IF(I30="","",INDEX('📦 Registro'!$N$4:$N$103,MATCH(I30,'📦 Registro'!$A$4:$A$103,0))),"")} | H30: =IFERROR(IF(F30="","",TODAY()-F30),"") | I30: {=IFERROR(INDEX(#REF!,MATCH(SMALL(IF(#REF!<>"",ROW(#REF!)-3),27),#REF!,0)),"")}
A31: {=IFERROR(IF(I31="","",INDEX('📦 Registro'!$A$4:$A$103,MATCH(I31,'📦 Registro'!$A$4:$A$103,0))),"")} | B31: {=IFERROR(IF(I31="","",INDEX('📦 Registro'!$B$4:$B$103,MATCH(I31,'📦 Registro'!$A$4:$A$103,0))),"")} | C31: {=IFERROR(IF(I31="","",INDEX('📦 Registro'!$D$4:$D$103,MATCH(I31,'📦 Registro'!$A$4:$A$103,0))),"")} | D31: {=IFERROR(IF(I31="","",INDEX('📦 Registro'!$E$4:$E$103,MATCH(I31,'📦 Registro'!$A$4:$A$103,0))),"")} | E31: {=IFERROR(IF(I31="","",INDEX('📦 Registro'!$I$4:$I$103,MATCH(I31,'📦 Registro'!$A$4:$A$103,0))),"")} | F31: {=IFERROR(IF(I31="","",INDEX('📦 Registro'!$C$4:$C$103,MATCH(I31,'📦 Registro'!$A$4:$A$103,0))),"")} | G31: {=IFERROR(IF(I31="","",INDEX('📦 Registro'!$N$4:$N$103,MATCH(I31,'📦 Registro'!$A$4:$A$103,0))),"")} | H31: =IFERROR(IF(F31="","",TODAY()-F31),"") | I31: {=IFERROR(INDEX(#REF!,MATCH(SMALL(IF(#REF!<>"",ROW(#REF!)-3),28),#REF!,0)),"")}
A32: {=IFERROR(IF(I32="","",INDEX('📦 Registro'!$A$4:$A$103,MATCH(I32,'📦 Registro'!$A$4:$A$103,0))),"")} | B32: {=IFERROR(IF(I32="","",INDEX('📦 Registro'!$B$4:$B$103,MATCH(I32,'📦 Registro'!$A$4:$A$103,0))),"")} | C32: {=IFERROR(IF(I32="","",INDEX('📦 Registro'!$D$4:$D$103,MATCH(I32,'📦 Registro'!$A$4:$A$103,0))),"")} | D32: {=IFERROR(IF(I32="","",INDEX('📦 Registro'!$E$4:$E$103,MATCH(I32,'📦 Registro'!$A$4:$A$103,0))),"")} | E32: {=IFERROR(IF(I32="","",INDEX('📦 Registro'!$I$4:$I$103,MATCH(I32,'📦 Registro'!$A$4:$A$103,0))),"")} | F32: {=IFERROR(IF(I32="","",INDEX('📦 Registro'!$C$4:$C$103,MATCH(I32,'📦 Registro'!$A$4:$A$103,0))),"")} | G32: {=IFERROR(IF(I32="","",INDEX('📦 Registro'!$N$4:$N$103,MATCH(I32,'📦 Registro'!$A$4:$A$103,0))),"")} | H32: =IFERROR(IF(F32="","",TODAY()-F32),"") | I32: {=IFERROR(INDEX(#REF!,MATCH(SMALL(IF(#REF!<>"",ROW(#REF!)-3),29),#REF!,0)),"")}
A33: {=IFERROR(IF(I33="","",INDEX('📦 Registro'!$A$4:$A$103,MATCH(I33,'📦 Registro'!$A$4:$A$103,0))),"")} | B33: {=IFERROR(IF(I33="","",INDEX('📦 Registro'!$B$4:$B$103,MATCH(I33,'📦 Registro'!$A$4:$A$103,0))),"")} | C33: {=IFERROR(IF(I33="","",INDEX('📦 Registro'!$D$4:$D$103,MATCH(I33,'📦 Registro'!$A$4:$A$103,0))),"")} | D33: {=IFERROR(IF(I33="","",INDEX('📦 Registro'!$E$4:$E$103,MATCH(I33,'📦 Registro'!$A$4:$A$103,0))),"")} | E33: {=IFERROR(IF(I33="","",INDEX('📦 Registro'!$I$4:$I$103,MATCH(I33,'📦 Registro'!$A$4:$A$103,0))),"")} | F33: {=IFERROR(IF(I33="","",INDEX('📦 Registro'!$C$4:$C$103,MATCH(I33,'📦 Registro'!$A$4:$A$103,0))),"")} | G33: {=IFERROR(IF(I33="","",INDEX('📦 Registro'!$N$4:$N$103,MATCH(I33,'📦 Registro'!$A$4:$A$103,0))),"")} | H33: =IFERROR(IF(F33="","",TODAY()-F33),"") | I33: {=IFERROR(INDEX(#REF!,MATCH(SMALL(IF(#REF!<>"",ROW(#REF!)-3),30),#REF!,0)),"")}
A34: {=IFERROR(IF(I34="","",INDEX('📦 Registro'!$A$4:$A$103,MATCH(I34,'📦 Registro'!$A$4:$A$103,0))),"")} | B34: {=IFERROR(IF(I34="","",INDEX('📦 Registro'!$B$4:$B$103,MATCH(I34,'📦 Registro'!$A$4:$A$103,0))),"")} | C34: {=IFERROR(IF(I34="","",INDEX('📦 Registro'!$D$4:$D$103,MATCH(I34,'📦 Registro'!$A$4:$A$103,0))),"")} | D34: {=IFERROR(IF(I34="","",INDEX('📦 Registro'!$E$4:$E$103,MATCH(I34,'📦 Registro'!$A$4:$A$103,0))),"")} | E34: {=IFERROR(IF(I34="","",INDEX('📦 Registro'!$I$4:$I$103,MATCH(I34,'📦 Registro'!$A$4:$A$103,0))),"")} | F34: {=IFERROR(IF(I34="","",INDEX('📦 Registro'!$C$4:$C$103,MATCH(I34,'📦 Registro'!$A$4:$A$103,0))),"")} | G34: {=IFERROR(IF(I34="","",INDEX('📦 Registro'!$N$4:$N$103,MATCH(I34,'📦 Registro'!$A$4:$A$103,0))),"")} | H34: =IFERROR(IF(F34="","",TODAY()-F34),"") | I34: {=IFERROR(INDEX(#REF!,MATCH(SMALL(IF(#REF!<>"",ROW(#REF!)-3),31),#REF!,0)),"")}
A35: {=IFERROR(IF(I35="","",INDEX('📦 Registro'!$A$4:$A$103,MATCH(I35,'📦 Registro'!$A$4:$A$103,0))),"")} | B35: {=IFERROR(IF(I35="","",INDEX('📦 Registro'!$B$4:$B$103,MATCH(I35,'📦 Registro'!$A$4:$A$103,0))),"")} | C35: {=IFERROR(IF(I35="","",INDEX('📦 Registro'!$D$4:$D$103,MATCH(I35,'📦 Registro'!$A$4:$A$103,0))),"")} | D35: {=IFERROR(IF(I35="","",INDEX('📦 Registro'!$E$4:$E$103,MATCH(I35,'📦 Registro'!$A$4:$A$103,0))),"")} | E35: {=IFERROR(IF(I35="","",INDEX('📦 Registro'!$I$4:$I$103,MATCH(I35,'📦 Registro'!$A$4:$A$103,0))),"")} | F35: {=IFERROR(IF(I35="","",INDEX('📦 Registro'!$C$4:$C$103,MATCH(I35,'📦 Registro'!$A$4:$A$103,0))),"")} | G35: {=IFERROR(IF(I35="","",INDEX('📦 Registro'!$N$4:$N$103,MATCH(I35,'📦 Registro'!$A$4:$A$103,0))),"")} | H35: =IFERROR(IF(F35="","",TODAY()-F35),"") | I35: {=IFERROR(INDEX(#REF!,MATCH(SMALL(IF(#REF!<>"",ROW(#REF!)-3),32),#REF!,0)),"")}
A36: {=IFERROR(IF(I36="","",INDEX('📦 Registro'!$A$4:$A$103,MATCH(I36,'📦 Registro'!$A$4:$A$103,0))),"")} | B36: {=IFERROR(IF(I36="","",INDEX('📦 Registro'!$B$4:$B$103,MATCH(I36,'📦 Registro'!$A$4:$A$103,0))),"")} | C36: {=IFERROR(IF(I36="","",INDEX('📦 Registro'!$D$4:$D$103,MATCH(I36,'📦 Registro'!$A$4:$A$103,0))),"")} | D36: {=IFERROR(IF(I36="","",INDEX('📦 Registro'!$E$4:$E$103,MATCH(I36,'📦 Registro'!$A$4:$A$103,0))),"")} | E36: {=IFERROR(IF(I36="","",INDEX('📦 Registro'!$I$4:$I$103,MATCH(I36,'📦 Registro'!$A$4:$A$103,0))),"")} | F36: {=IFERROR(IF(I36="","",INDEX('📦 Registro'!$C$4:$C$103,MATCH(I36,'📦 Registro'!$A$4:$A$103,0))),"")} | G36: {=IFERROR(IF(I36="","",INDEX('📦 Registro'!$N$4:$N$103,MATCH(I36,'📦 Registro'!$A$4:$A$103,0))),"")} | H36: =IFERROR(IF(F36="","",TODAY()-F36),"") | I36: {=IFERROR(INDEX(#REF!,MATCH(SMALL(IF(#REF!<>"",ROW(#REF!)-3),33),#REF!,0)),"")}
A37: {=IFERROR(IF(I37="","",INDEX('📦 Registro'!$A$4:$A$103,MATCH(I37,'📦 Registro'!$A$4:$A$103,0))),"")} | B37: {=IFERROR(IF(I37="","",INDEX('📦 Registro'!$B$4:$B$103,MATCH(I37,'📦 Registro'!$A$4:$A$103,0))),"")} | C37: {=IFERROR(IF(I37="","",INDEX('📦 Registro'!$D$4:$D$103,MATCH(I37,'📦 Registro'!$A$4:$A$103,0))),"")} | D37: {=IFERROR(IF(I37="","",INDEX('📦 Registro'!$E$4:$E$103,MATCH(I37,'📦 Registro'!$A$4:$A$103,0))),"")} | E37: {=IFERROR(IF(I37="","",INDEX('📦 Registro'!$I$4:$I$103,MATCH(I37,'📦 Registro'!$A$4:$A$103,0))),"")} | F37: {=IFERROR(IF(I37="","",INDEX('📦 Registro'!$C$4:$C$103,MATCH(I37,'📦 Registro'!$A$4:$A$103,0))),"")} | G37: {=IFERROR(IF(I37="","",INDEX('📦 Registro'!$N$4:$N$103,MATCH(I37,'📦 Registro'!$A$4:$A$103,0))),"")} | H37: =IFERROR(IF(F37="","",TODAY()-F37),"") | I37: {=IFERROR(INDEX(#REF!,MATCH(SMALL(IF(#REF!<>"",ROW(#REF!)-3),34),#REF!,0)),"")}
A38: {=IFERROR(IF(I38="","",INDEX('📦 Registro'!$A$4:$A$103,MATCH(I38,'📦 Registro'!$A$4:$A$103,0))),"")} | B38: {=IFERROR(IF(I38="","",INDEX('📦 Registro'!$B$4:$B$103,MATCH(I38,'📦 Registro'!$A$4:$A$103,0))),"")} | C38: {=IFERROR(IF(I38="","",INDEX('📦 Registro'!$D$4:$D$103,MATCH(I38,'📦 Registro'!$A$4:$A$103,0))),"")} | D38: {=IFERROR(IF(I38="","",INDEX('📦 Registro'!$E$4:$E$103,MATCH(I38,'📦 Registro'!$A$4:$A$103,0))),"")} | E38: {=IFERROR(IF(I38="","",INDEX('📦 Registro'!$I$4:$I$103,MATCH(I38,'📦 Registro'!$A$4:$A$103,0))),"")} | F38: {=IFERROR(IF(I38="","",INDEX('📦 Registro'!$C$4:$C$103,MATCH(I38,'📦 Registro'!$A$4:$A$103,0))),"")} | G38: {=IFERROR(IF(I38="","",INDEX('📦 Registro'!$N$4:$N$103,MATCH(I38,'📦 Registro'!$A$4:$A$103,0))),"")} | H38: =IFERROR(IF(F38="","",TODAY()-F38),"") | I38: {=IFERROR(INDEX(#REF!,MATCH(SMALL(IF(#REF!<>"",ROW(#REF!)-3),35),#REF!,0)),"")}
A39: {=IFERROR(IF(I39="","",INDEX('📦 Registro'!$A$4:$A$103,MATCH(I39,'📦 Registro'!$A$4:$A$103,0))),"")} | B39: {=IFERROR(IF(I39="","",INDEX('📦 Registro'!$B$4:$B$103,MATCH(I39,'📦 Registro'!$A$4:$A$103,0))),"")} | C39: {=IFERROR(IF(I39="","",INDEX('📦 Registro'!$D$4:$D$103,MATCH(I39,'📦 Registro'!$A$4:$A$103,0))),"")} | D39: {=IFERROR(IF(I39="","",INDEX('📦 Registro'!$E$4:$E$103,MATCH(I39,'📦 Registro'!$A$4:$A$103,0))),"")} | E39: {=IFERROR(IF(I39="","",INDEX('📦 Registro'!$I$4:$I$103,MATCH(I39,'📦 Registro'!$A$4:$A$103,0))),"")} | F39: {=IFERROR(IF(I39="","",INDEX('📦 Registro'!$C$4:$C$103,MATCH(I39,'📦 Registro'!$A$4:$A$103,0))),"")} | G39: {=IFERROR(IF(I39="","",INDEX('📦 Registro'!$N$4:$N$103,MATCH(I39,'📦 Registro'!$A$4:$A$103,0))),"")} | H39: =IFERROR(IF(F39="","",TODAY()-F39),"") | I39: {=IFERROR(INDEX(#REF!,MATCH(SMALL(IF(#REF!<>"",ROW(#REF!)-3),36),#REF!,0)),"")}
A40: {=IFERROR(IF(I40="","",INDEX('📦 Registro'!$A$4:$A$103,MATCH(I40,'📦 Registro'!$A$4:$A$103,0))),"")} | B40: {=IFERROR(IF(I40="","",INDEX('📦 Registro'!$B$4:$B$103,MATCH(I40,'📦 Registro'!$A$4:$A$103,0))),"")} | C40: {=IFERROR(IF(I40="","",INDEX('📦 Registro'!$D$4:$D$103,MATCH(I40,'📦 Registro'!$A$4:$A$103,0))),"")} | D40: {=IFERROR(IF(I40="","",INDEX('📦 Registro'!$E$4:$E$103,MATCH(I40,'📦 Registro'!$A$4:$A$103,0))),"")} | E40: {=IFERROR(IF(I40="","",INDEX('📦 Registro'!$I$4:$I$103,MATCH(I40,'📦 Registro'!$A$4:$A$103,0))),"")} | F40: {=IFERROR(IF(I40="","",INDEX('📦 Registro'!$C$4:$C$103,MATCH(I40,'📦 Registro'!$A$4:$A$103,0))),"")} | G40: {=IFERROR(IF(I40="","",INDEX('📦 Registro'!$N$4:$N$103,MATCH(I40,'📦 Registro'!$A$4:$A$103,0))),"")} | H40: =IFERROR(IF(F40="","",TODAY()-F40),"") | I40: {=IFERROR(INDEX(#REF!,MATCH(SMALL(IF(#REF!<>"",ROW(#REF!)-3),37),#REF!,0)),"")}
A41: {=IFERROR(IF(I41="","",INDEX('📦 Registro'!$A$4:$A$103,MATCH(I41,'📦 Registro'!$A$4:$A$103,0))),"")} | B41: {=IFERROR(IF(I41="","",INDEX('📦 Registro'!$B$4:$B$103,MATCH(I41,'📦 Registro'!$A$4:$A$103,0))),"")} | C41: {=IFERROR(IF(I41="","",INDEX('📦 Registro'!$D$4:$D$103,MATCH(I41,'📦 Registro'!$A$4:$A$103,0))),"")} | D41: {=IFERROR(IF(I41="","",INDEX('📦 Registro'!$E$4:$E$103,MATCH(I41,'📦 Registro'!$A$4:$A$103,0))),"")} | E41: {=IFERROR(IF(I41="","",INDEX('📦 Registro'!$I$4:$I$103,MATCH(I41,'📦 Registro'!$A$4:$A$103,0))),"")} | F41: {=IFERROR(IF(I41="","",INDEX('📦 Registro'!$C$4:$C$103,MATCH(I41,'📦 Registro'!$A$4:$A$103,0))),"")} | G41: {=IFERROR(IF(I41="","",INDEX('📦 Registro'!$N$4:$N$103,MATCH(I41,'📦 Registro'!$A$4:$A$103,0))),"")} | H41: =IFERROR(IF(F41="","",TODAY()-F41),"") | I41: {=IFERROR(INDEX(#REF!,MATCH(SMALL(IF(#REF!<>"",ROW(#REF!)-3),38),#REF!,0)),"")}
A42: {=IFERROR(IF(I42="","",INDEX('📦 Registro'!$A$4:$A$103,MATCH(I42,'📦 Registro'!$A$4:$A$103,0))),"")} | B42: {=IFERROR(IF(I42="","",INDEX('📦 Registro'!$B$4:$B$103,MATCH(I42,'📦 Registro'!$A$4:$A$103,0))),"")} | C42: {=IFERROR(IF(I42="","",INDEX('📦 Registro'!$D$4:$D$103,MATCH(I42,'📦 Registro'!$A$4:$A$103,0))),"")} | D42: {=IFERROR(IF(I42="","",INDEX('📦 Registro'!$E$4:$E$103,MATCH(I42,'📦 Registro'!$A$4:$A$103,0))),"")} | E42: {=IFERROR(IF(I42="","",INDEX('📦 Registro'!$I$4:$I$103,MATCH(I42,'📦 Registro'!$A$4:$A$103,0))),"")} | F42: {=IFERROR(IF(I42="","",INDEX('📦 Registro'!$C$4:$C$103,MATCH(I42,'📦 Registro'!$A$4:$A$103,0))),"")} | G42: {=IFERROR(IF(I42="","",INDEX('📦 Registro'!$N$4:$N$103,MATCH(I42,'📦 Registro'!$A$4:$A$103,0))),"")} | H42: =IFERROR(IF(F42="","",TODAY()-F42),"") | I42: {=IFERROR(INDEX(#REF!,MATCH(SMALL(IF(#REF!<>"",ROW(#REF!)-3),39),#REF!,0)),"")}
A43: {=IFERROR(IF(I43="","",INDEX('📦 Registro'!$A$4:$A$103,MATCH(I43,'📦 Registro'!$A$4:$A$103,0))),"")} | B43: {=IFERROR(IF(I43="","",INDEX('📦 Registro'!$B$4:$B$103,MATCH(I43,'📦 Registro'!$A$4:$A$103,0))),"")} | C43: {=IFERROR(IF(I43="","",INDEX('📦 Registro'!$D$4:$D$103,MATCH(I43,'📦 Registro'!$A$4:$A$103,0))),"")} | D43: {=IFERROR(IF(I43="","",INDEX('📦 Registro'!$E$4:$E$103,MATCH(I43,'📦 Registro'!$A$4:$A$103,0))),"")} | E43: {=IFERROR(IF(I43="","",INDEX('📦 Registro'!$I$4:$I$103,MATCH(I43,'📦 Registro'!$A$4:$A$103,0))),"")} | F43: {=IFERROR(IF(I43="","",INDEX('📦 Registro'!$C$4:$C$103,MATCH(I43,'📦 Registro'!$A$4:$A$103,0))),"")} | G43: {=IFERROR(IF(I43="","",INDEX('📦 Registro'!$N$4:$N$103,MATCH(I43,'📦 Registro'!$A$4:$A$103,0))),"")} | H43: =IFERROR(IF(F43="","",TODAY()-F43),"") | I43: {=IFERROR(INDEX(#REF!,MATCH(SMALL(IF(#REF!<>"",ROW(#REF!)-3),40),#REF!,0)),"")}
A44: {=IFERROR(IF(I44="","",INDEX('📦 Registro'!$A$4:$A$103,MATCH(I44,'📦 Registro'!$A$4:$A$103,0))),"")} | B44: {=IFERROR(IF(I44="","",INDEX('📦 Registro'!$B$4:$B$103,MATCH(I44,'📦 Registro'!$A$4:$A$103,0))),"")} | C44: {=IFERROR(IF(I44="","",INDEX('📦 Registro'!$D$4:$D$103,MATCH(I44,'📦 Registro'!$A$4:$A$103,0))),"")} | D44: {=IFERROR(IF(I44="","",INDEX('📦 Registro'!$E$4:$E$103,MATCH(I44,'📦 Registro'!$A$4:$A$103,0))),"")} | E44: {=IFERROR(IF(I44="","",INDEX('📦 Registro'!$I$4:$I$103,MATCH(I44,'📦 Registro'!$A$4:$A$103,0))),"")} | F44: {=IFERROR(IF(I44="","",INDEX('📦 Registro'!$C$4:$C$103,MATCH(I44,'📦 Registro'!$A$4:$A$103,0))),"")} | G44: {=IFERROR(IF(I44="","",INDEX('📦 Registro'!$N$4:$N$103,MATCH(I44,'📦 Registro'!$A$4:$A$103,0))),"")} | H44: =IFERROR(IF(F44="","",TODAY()-F44),"") | I44: {=IFERROR(INDEX(#REF!,MATCH(SMALL(IF(#REF!<>"",ROW(#REF!)-3),41),#REF!,0)),"")}
A45: {=IFERROR(IF(I45="","",INDEX('📦 Registro'!$A$4:$A$103,MATCH(I45,'📦 Registro'!$A$4:$A$103,0))),"")} | B45: {=IFERROR(IF(I45="","",INDEX('📦 Registro'!$B$4:$B$103,MATCH(I45,'📦 Registro'!$A$4:$A$103,0))),"")} | C45: {=IFERROR(IF(I45="","",INDEX('📦 Registro'!$D$4:$D$103,MATCH(I45,'📦 Registro'!$A$4:$A$103,0))),"")} | D45: {=IFERROR(IF(I45="","",INDEX('📦 Registro'!$E$4:$E$103,MATCH(I45,'📦 Registro'!$A$4:$A$103,0))),"")} | E45: {=IFERROR(IF(I45="","",INDEX('📦 Registro'!$I$4:$I$103,MATCH(I45,'📦 Registro'!$A$4:$A$103,0))),"")} | F45: {=IFERROR(IF(I45="","",INDEX('📦 Registro'!$C$4:$C$103,MATCH(I45,'📦 Registro'!$A$4:$A$103,0))),"")} | G45: {=IFERROR(IF(I45="","",INDEX('📦 Registro'!$N$4:$N$103,MATCH(I45,'📦 Registro'!$A$4:$A$103,0))),"")} | H45: =IFERROR(IF(F45="","",TODAY()-F45),"") | I45: {=IFERROR(INDEX(#REF!,MATCH(SMALL(IF(#REF!<>"",ROW(#REF!)-3),42),#REF!,0)),"")}
A46: {=IFERROR(IF(I46="","",INDEX('📦 Registro'!$A$4:$A$103,MATCH(I46,'📦 Registro'!$A$4:$A$103,0))),"")} | B46: {=IFERROR(IF(I46="","",INDEX('📦 Registro'!$B$4:$B$103,MATCH(I46,'📦 Registro'!$A$4:$A$103,0))),"")} | C46: {=IFERROR(IF(I46="","",INDEX('📦 Registro'!$D$4:$D$103,MATCH(I46,'📦 Registro'!$A$4:$A$103,0))),"")} | D46: {=IFERROR(IF(I46="","",INDEX('📦 Registro'!$E$4:$E$103,MATCH(I46,'📦 Registro'!$A$4:$A$103,0))),"")} | E46: {=IFERROR(IF(I46="","",INDEX('📦 Registro'!$I$4:$I$103,MATCH(I46,'📦 Registro'!$A$4:$A$103,0))),"")} | F46: {=IFERROR(IF(I46="","",INDEX('📦 Registro'!$C$4:$C$103,MATCH(I46,'📦 Registro'!$A$4:$A$103,0))),"")} | G46: {=IFERROR(IF(I46="","",INDEX('📦 Registro'!$N$4:$N$103,MATCH(I46,'📦 Registro'!$A$4:$A$103,0))),"")} | H46: =IFERROR(IF(F46="","",TODAY()-F46),"") | I46: {=IFERROR(INDEX(#REF!,MATCH(SMALL(IF(#REF!<>"",ROW(#REF!)-3),43),#REF!,0)),"")}
A47: {=IFERROR(IF(I47="","",INDEX('📦 Registro'!$A$4:$A$103,MATCH(I47,'📦 Registro'!$A$4:$A$103,0))),"")} | B47: {=IFERROR(IF(I47="","",INDEX('📦 Registro'!$B$4:$B$103,MATCH(I47,'📦 Registro'!$A$4:$A$103,0))),"")} | C47: {=IFERROR(IF(I47="","",INDEX('📦 Registro'!$D$4:$D$103,MATCH(I47,'📦 Registro'!$A$4:$A$103,0))),"")} | D47: {=IFERROR(IF(I47="","",INDEX('📦 Registro'!$E$4:$E$103,MATCH(I47,'📦 Registro'!$A$4:$A$103,0))),"")} | E47: {=IFERROR(IF(I47="","",INDEX('📦 Registro'!$I$4:$I$103,MATCH(I47,'📦 Registro'!$A$4:$A$103,0))),"")} | F47: {=IFERROR(IF(I47="","",INDEX('📦 Registro'!$C$4:$C$103,MATCH(I47,'📦 Registro'!$A$4:$A$103,0))),"")} | G47: {=IFERROR(IF(I47="","",INDEX('📦 Registro'!$N$4:$N$103,MATCH(I47,'📦 Registro'!$A$4:$A$103,0))),"")} | H47: =IFERROR(IF(F47="","",TODAY()-F47),"") | I47: {=IFERROR(INDEX(#REF!,MATCH(SMALL(IF(#REF!<>"",ROW(#REF!)-3),44),#REF!,0)),"")}
A48: {=IFERROR(IF(I48="","",INDEX('📦 Registro'!$A$4:$A$103,MATCH(I48,'📦 Registro'!$A$4:$A$103,0))),"")} | B48: {=IFERROR(IF(I48="","",INDEX('📦 Registro'!$B$4:$B$103,MATCH(I48,'📦 Registro'!$A$4:$A$103,0))),"")} | C48: {=IFERROR(IF(I48="","",INDEX('📦 Registro'!$D$4:$D$103,MATCH(I48,'📦 Registro'!$A$4:$A$103,0))),"")} | D48: {=IFERROR(IF(I48="","",INDEX('📦 Registro'!$E$4:$E$103,MATCH(I48,'📦 Registro'!$A$4:$A$103,0))),"")} | E48: {=IFERROR(IF(I48="","",INDEX('📦 Registro'!$I$4:$I$103,MATCH(I48,'📦 Registro'!$A$4:$A$103,0))),"")} | F48: {=IFERROR(IF(I48="","",INDEX('📦 Registro'!$C$4:$C$103,MATCH(I48,'📦 Registro'!$A$4:$A$103,0))),"")} | G48: {=IFERROR(IF(I48="","",INDEX('📦 Registro'!$N$4:$N$103,MATCH(I48,'📦 Registro'!$A$4:$A$103,0))),"")} | H48: =IFERROR(IF(F48="","",TODAY()-F48),"") | I48: {=IFERROR(INDEX(#REF!,MATCH(SMALL(IF(#REF!<>"",ROW(#REF!)-3),45),#REF!,0)),"")}
A49: {=IFERROR(IF(I49="","",INDEX('📦 Registro'!$A$4:$A$103,MATCH(I49,'📦 Registro'!$A$4:$A$103,0))),"")} | B49: {=IFERROR(IF(I49="","",INDEX('📦 Registro'!$B$4:$B$103,MATCH(I49,'📦 Registro'!$A$4:$A$103,0))),"")} | C49: {=IFERROR(IF(I49="","",INDEX('📦 Registro'!$D$4:$D$103,MATCH(I49,'📦 Registro'!$A$4:$A$103,0))),"")} | D49: {=IFERROR(IF(I49="","",INDEX('📦 Registro'!$E$4:$E$103,MATCH(I49,'📦 Registro'!$A$4:$A$103,0))),"")} | E49: {=IFERROR(IF(I49="","",INDEX('📦 Registro'!$I$4:$I$103,MATCH(I49,'📦 Registro'!$A$4:$A$103,0))),"")} | F49: {=IFERROR(IF(I49="","",INDEX('📦 Registro'!$C$4:$C$103,MATCH(I49,'📦 Registro'!$A$4:$A$103,0))),"")} | G49: {=IFERROR(IF(I49="","",INDEX('📦 Registro'!$N$4:$N$103,MATCH(I49,'📦 Registro'!$A$4:$A$103,0))),"")} | H49: =IFERROR(IF(F49="","",TODAY()-F49),"") | I49: {=IFERROR(INDEX(#REF!,MATCH(SMALL(IF(#REF!<>"",ROW(#REF!)-3),46),#REF!,0)),"")}
A50: {=IFERROR(IF(I50="","",INDEX('📦 Registro'!$A$4:$A$103,MATCH(I50,'📦 Registro'!$A$4:$A$103,0))),"")} | B50: {=IFERROR(IF(I50="","",INDEX('📦 Registro'!$B$4:$B$103,MATCH(I50,'📦 Registro'!$A$4:$A$103,0))),"")} | C50: {=IFERROR(IF(I50="","",INDEX('📦 Registro'!$D$4:$D$103,MATCH(I50,'📦 Registro'!$A$4:$A$103,0))),"")} | D50: {=IFERROR(IF(I50="","",INDEX('📦 Registro'!$E$4:$E$103,MATCH(I50,'📦 Registro'!$A$4:$A$103,0))),"")} | E50: {=IFERROR(IF(I50="","",INDEX('📦 Registro'!$I$4:$I$103,MATCH(I50,'📦 Registro'!$A$4:$A$103,0))),"")} | F50: {=IFERROR(IF(I50="","",INDEX('📦 Registro'!$C$4:$C$103,MATCH(I50,'📦 Registro'!$A$4:$A$103,0))),"")} | G50: {=IFERROR(IF(I50="","",INDEX('📦 Registro'!$N$4:$N$103,MATCH(I50,'📦 Registro'!$A$4:$A$103,0))),"")} | H50: =IFERROR(IF(F50="","",TODAY()-F50),"") | I50: {=IFERROR(INDEX(#REF!,MATCH(SMALL(IF(#REF!<>"",ROW(#REF!)-3),47),#REF!,0)),"")}
A51: {=IFERROR(IF(I51="","",INDEX('📦 Registro'!$A$4:$A$103,MATCH(I51,'📦 Registro'!$A$4:$A$103,0))),"")} | B51: {=IFERROR(IF(I51="","",INDEX('📦 Registro'!$B$4:$B$103,MATCH(I51,'📦 Registro'!$A$4:$A$103,0))),"")} | C51: {=IFERROR(IF(I51="","",INDEX('📦 Registro'!$D$4:$D$103,MATCH(I51,'📦 Registro'!$A$4:$A$103,0))),"")} | D51: {=IFERROR(IF(I51="","",INDEX('📦 Registro'!$E$4:$E$103,MATCH(I51,'📦 Registro'!$A$4:$A$103,0))),"")} | E51: {=IFERROR(IF(I51="","",INDEX('📦 Registro'!$I$4:$I$103,MATCH(I51,'📦 Registro'!$A$4:$A$103,0))),"")} | F51: {=IFERROR(IF(I51="","",INDEX('📦 Registro'!$C$4:$C$103,MATCH(I51,'📦 Registro'!$A$4:$A$103,0))),"")} | G51: {=IFERROR(IF(I51="","",INDEX('📦 Registro'!$N$4:$N$103,MATCH(I51,'📦 Registro'!$A$4:$A$103,0))),"")} | H51: =IFERROR(IF(F51="","",TODAY()-F51),"") | I51: {=IFERROR(INDEX(#REF!,MATCH(SMALL(IF(#REF!<>"",ROW(#REF!)-3),48),#REF!,0)),"")}
A52: {=IFERROR(IF(I52="","",INDEX('📦 Registro'!$A$4:$A$103,MATCH(I52,'📦 Registro'!$A$4:$A$103,0))),"")} | B52: {=IFERROR(IF(I52="","",INDEX('📦 Registro'!$B$4:$B$103,MATCH(I52,'📦 Registro'!$A$4:$A$103,0))),"")} | C52: {=IFERROR(IF(I52="","",INDEX('📦 Registro'!$D$4:$D$103,MATCH(I52,'📦 Registro'!$A$4:$A$103,0))),"")} | D52: {=IFERROR(IF(I52="","",INDEX('📦 Registro'!$E$4:$E$103,MATCH(I52,'📦 Registro'!$A$4:$A$103,0))),"")} | E52: {=IFERROR(IF(I52="","",INDEX('📦 Registro'!$I$4:$I$103,MATCH(I52,'📦 Registro'!$A$4:$A$103,0))),"")} | F52: {=IFERROR(IF(I52="","",INDEX('📦 Registro'!$C$4:$C$103,MATCH(I52,'📦 Registro'!$A$4:$A$103,0))),"")} | G52: {=IFERROR(IF(I52="","",INDEX('📦 Registro'!$N$4:$N$103,MATCH(I52,'📦 Registro'!$A$4:$A$103,0))),"")} | H52: =IFERROR(IF(F52="","",TODAY()-F52),"") | I52: {=IFERROR(INDEX(#REF!,MATCH(SMALL(IF(#REF!<>"",ROW(#REF!)-3),49),#REF!,0)),"")}
A53: {=IFERROR(IF(I53="","",INDEX('📦 Registro'!$A$4:$A$103,MATCH(I53,'📦 Registro'!$A$4:$A$103,0))),"")} | B53: {=IFERROR(IF(I53="","",INDEX('📦 Registro'!$B$4:$B$103,MATCH(I53,'📦 Registro'!$A$4:$A$103,0))),"")} | C53: {=IFERROR(IF(I53="","",INDEX('📦 Registro'!$D$4:$D$103,MATCH(I53,'📦 Registro'!$A$4:$A$103,0))),"")} | D53: {=IFERROR(IF(I53="","",INDEX('📦 Registro'!$E$4:$E$103,MATCH(I53,'📦 Registro'!$A$4:$A$103,0))),"")} | E53: {=IFERROR(IF(I53="","",INDEX('📦 Registro'!$I$4:$I$103,MATCH(I53,'📦 Registro'!$A$4:$A$103,0))),"")} | F53: {=IFERROR(IF(I53="","",INDEX('📦 Registro'!$C$4:$C$103,MATCH(I53,'📦 Registro'!$A$4:$A$103,0))),"")} | G53: {=IFERROR(IF(I53="","",INDEX('📦 Registro'!$N$4:$N$103,MATCH(I53,'📦 Registro'!$A$4:$A$103,0))),"")} | H53: =IFERROR(IF(F53="","",TODAY()-F53),"") | I53: {=IFERROR(INDEX(#REF!,MATCH(SMALL(IF(#REF!<>"",ROW(#REF!)-3),50),#REF!,0)),"")}
A54: {=IFERROR(IF(I54="","",INDEX('📦 Registro'!$A$4:$A$103,MATCH(I54,'📦 Registro'!$A$4:$A$103,0))),"")} | B54: {=IFERROR(IF(I54="","",INDEX('📦 Registro'!$B$4:$B$103,MATCH(I54,'📦 Registro'!$A$4:$A$103,0))),"")} | C54: {=IFERROR(IF(I54="","",INDEX('📦 Registro'!$D$4:$D$103,MATCH(I54,'📦 Registro'!$A$4:$A$103,0))),"")} | D54: {=IFERROR(IF(I54="","",INDEX('📦 Registro'!$E$4:$E$103,MATCH(I54,'📦 Registro'!$A$4:$A$103,0))),"")} | E54: {=IFERROR(IF(I54="","",INDEX('📦 Registro'!$I$4:$I$103,MATCH(I54,'📦 Registro'!$A$4:$A$103,0))),"")} | F54: {=IFERROR(IF(I54="","",INDEX('📦 Registro'!$C$4:$C$103,MATCH(I54,'📦 Registro'!$A$4:$A$103,0))),"")} | G54: {=IFERROR(IF(I54="","",INDEX('📦 Registro'!$N$4:$N$103,MATCH(I54,'📦 Registro'!$A$4:$A$103,0))),"")} | H54: =IFERROR(IF(F54="","",TODAY()-F54),"") | I54: {=IFERROR(INDEX(#REF!,MATCH(SMALL(IF(#REF!<>"",ROW(#REF!)-3),51),#REF!,0)),"")}
A55: {=IFERROR(IF(I55="","",INDEX('📦 Registro'!$A$4:$A$103,MATCH(I55,'📦 Registro'!$A$4:$A$103,0))),"")} | B55: {=IFERROR(IF(I55="","",INDEX('📦 Registro'!$B$4:$B$103,MATCH(I55,'📦 Registro'!$A$4:$A$103,0))),"")} | C55: {=IFERROR(IF(I55="","",INDEX('📦 Registro'!$D$4:$D$103,MATCH(I55,'📦 Registro'!$A$4:$A$103,0))),"")} | D55: {=IFERROR(IF(I55="","",INDEX('📦 Registro'!$E$4:$E$103,MATCH(I55,'📦 Registro'!$A$4:$A$103,0))),"")} | E55: {=IFERROR(IF(I55="","",INDEX('📦 Registro'!$I$4:$I$103,MATCH(I55,'📦 Registro'!$A$4:$A$103,0))),"")} | F55: {=IFERROR(IF(I55="","",INDEX('📦 Registro'!$C$4:$C$103,MATCH(I55,'📦 Registro'!$A$4:$A$103,0))),"")} | G55: {=IFERROR(IF(I55="","",INDEX('📦 Registro'!$N$4:$N$103,MATCH(I55,'📦 Registro'!$A$4:$A$103,0))),"")} | H55: =IFERROR(IF(F55="","",TODAY()-F55),"") | I55: {=IFERROR(INDEX(#REF!,MATCH(SMALL(IF(#REF!<>"",ROW(#REF!)-3),52),#REF!,0)),"")}
A56: {=IFERROR(IF(I56="","",INDEX('📦 Registro'!$A$4:$A$103,MATCH(I56,'📦 Registro'!$A$4:$A$103,0))),"")} | B56: {=IFERROR(IF(I56="","",INDEX('📦 Registro'!$B$4:$B$103,MATCH(I56,'📦 Registro'!$A$4:$A$103,0))),"")} | C56: {=IFERROR(IF(I56="","",INDEX('📦 Registro'!$D$4:$D$103,MATCH(I56,'📦 Registro'!$A$4:$A$103,0))),"")} | D56: {=IFERROR(IF(I56="","",INDEX('📦 Registro'!$E$4:$E$103,MATCH(I56,'📦 Registro'!$A$4:$A$103,0))),"")} | E56: {=IFERROR(IF(I56="","",INDEX('📦 Registro'!$I$4:$I$103,MATCH(I56,'📦 Registro'!$A$4:$A$103,0))),"")} | F56: {=IFERROR(IF(I56="","",INDEX('📦 Registro'!$C$4:$C$103,MATCH(I56,'📦 Registro'!$A$4:$A$103,0))),"")} | G56: {=IFERROR(IF(I56="","",INDEX('📦 Registro'!$N$4:$N$103,MATCH(I56,'📦 Registro'!$A$4:$A$103,0))),"")} | H56: =IFERROR(IF(F56="","",TODAY()-F56),"") | I56: {=IFERROR(INDEX(#REF!,MATCH(SMALL(IF(#REF!<>"",ROW(#REF!)-3),53),#REF!,0)),"")}
A57: {=IFERROR(IF(I57="","",INDEX('📦 Registro'!$A$4:$A$103,MATCH(I57,'📦 Registro'!$A$4:$A$103,0))),"")} | B57: {=IFERROR(IF(I57="","",INDEX('📦 Registro'!$B$4:$B$103,MATCH(I57,'📦 Registro'!$A$4:$A$103,0))),"")} | C57: {=IFERROR(IF(I57="","",INDEX('📦 Registro'!$D$4:$D$103,MATCH(I57,'📦 Registro'!$A$4:$A$103,0))),"")} | D57: {=IFERROR(IF(I57="","",INDEX('📦 Registro'!$E$4:$E$103,MATCH(I57,'📦 Registro'!$A$4:$A$103,0))),"")} | E57: {=IFERROR(IF(I57="","",INDEX('📦 Registro'!$I$4:$I$103,MATCH(I57,'📦 Registro'!$A$4:$A$103,0))),"")} | F57: {=IFERROR(IF(I57="","",INDEX('📦 Registro'!$C$4:$C$103,MATCH(I57,'📦 Registro'!$A$4:$A$103,0))),"")} | G57: {=IFERROR(IF(I57="","",INDEX('📦 Registro'!$N$4:$N$103,MATCH(I57,'📦 Registro'!$A$4:$A$103,0))),"")} | H57: =IFERROR(IF(F57="","",TODAY()-F57),"") | I57: {=IFERROR(INDEX(#REF!,MATCH(SMALL(IF(#REF!<>"",ROW(#REF!)-3),54),#REF!,0)),"")}
A58: {=IFERROR(IF(I58="","",INDEX('📦 Registro'!$A$4:$A$103,MATCH(I58,'📦 Registro'!$A$4:$A$103,0))),"")} | B58: {=IFERROR(IF(I58="","",INDEX('📦 Registro'!$B$4:$B$103,MATCH(I58,'📦 Registro'!$A$4:$A$103,0))),"")} | C58: {=IFERROR(IF(I58="","",INDEX('📦 Registro'!$D$4:$D$103,MATCH(I58,'📦 Registro'!$A$4:$A$103,0))),"")} | D58: {=IFERROR(IF(I58="","",INDEX('📦 Registro'!$E$4:$E$103,MATCH(I58,'📦 Registro'!$A$4:$A$103,0))),"")} | E58: {=IFERROR(IF(I58="","",INDEX('📦 Registro'!$I$4:$I$103,MATCH(I58,'📦 Registro'!$A$4:$A$103,0))),"")} | F58: {=IFERROR(IF(I58="","",INDEX('📦 Registro'!$C$4:$C$103,MATCH(I58,'📦 Registro'!$A$4:$A$103,0))),"")} | G58: {=IFERROR(IF(I58="","",INDEX('📦 Registro'!$N$4:$N$103,MATCH(I58,'📦 Registro'!$A$4:$A$103,0))),"")} | H58: =IFERROR(IF(F58="","",TODAY()-F58),"") | I58: {=IFERROR(INDEX(#REF!,MATCH(SMALL(IF(#REF!<>"",ROW(#REF!)-3),55),#REF!,0)),"")}
A59: {=IFERROR(IF(I59="","",INDEX('📦 Registro'!$A$4:$A$103,MATCH(I59,'📦 Registro'!$A$4:$A$103,0))),"")} | B59: {=IFERROR(IF(I59="","",INDEX('📦 Registro'!$B$4:$B$103,MATCH(I59,'📦 Registro'!$A$4:$A$103,0))),"")} | C59: {=IFERROR(IF(I59="","",INDEX('📦 Registro'!$D$4:$D$103,MATCH(I59,'📦 Registro'!$A$4:$A$103,0))),"")} | D59: {=IFERROR(IF(I59="","",INDEX('📦 Registro'!$E$4:$E$103,MATCH(I59,'📦 Registro'!$A$4:$A$103,0))),"")} | E59: {=IFERROR(IF(I59="","",INDEX('📦 Registro'!$I$4:$I$103,MATCH(I59,'📦 Registro'!$A$4:$A$103,0))),"")} | F59: {=IFERROR(IF(I59="","",INDEX('📦 Registro'!$C$4:$C$103,MATCH(I59,'📦 Registro'!$A$4:$A$103,0))),"")} | G59: {=IFERROR(IF(I59="","",INDEX('📦 Registro'!$N$4:$N$103,MATCH(I59,'📦 Registro'!$A$4:$A$103,0))),"")} | H59: =IFERROR(IF(F59="","",TODAY()-F59),"") | I59: {=IFERROR(INDEX(#REF!,MATCH(SMALL(IF(#REF!<>"",ROW(#REF!)-3),56),#REF!,0)),"")}
A60: {=IFERROR(IF(I60="","",INDEX('📦 Registro'!$A$4:$A$103,MATCH(I60,'📦 Registro'!$A$4:$A$103,0))),"")} | B60: {=IFERROR(IF(I60="","",INDEX('📦 Registro'!$B$4:$B$103,MATCH(I60,'📦 Registro'!$A$4:$A$103,0))),"")} | C60: {=IFERROR(IF(I60="","",INDEX('📦 Registro'!$D$4:$D$103,MATCH(I60,'📦 Registro'!$A$4:$A$103,0))),"")} | D60: {=IFERROR(IF(I60="","",INDEX('📦 Registro'!$E$4:$E$103,MATCH(I60,'📦 Registro'!$A$4:$A$103,0))),"")} | E60: {=IFERROR(IF(I60="","",INDEX('📦 Registro'!$I$4:$I$103,MATCH(I60,'📦 Registro'!$A$4:$A$103,0))),"")} | F60: {=IFERROR(IF(I60="","",INDEX('📦 Registro'!$C$4:$C$103,MATCH(I60,'📦 Registro'!$A$4:$A$103,0))),"")} | G60: {=IFERROR(IF(I60="","",INDEX('📦 Registro'!$N$4:$N$103,MATCH(I60,'📦 Registro'!$A$4:$A$103,0))),"")} | H60: =IFERROR(IF(F60="","",TODAY()-F60),"") | I60: {=IFERROR(INDEX(#REF!,MATCH(SMALL(IF(#REF!<>"",ROW(#REF!)-3),57),#REF!,0)),"")}
A61: {=IFERROR(IF(I61="","",INDEX('📦 Registro'!$A$4:$A$103,MATCH(I61,'📦 Registro'!$A$4:$A$103,0))),"")} | B61: {=IFERROR(IF(I61="","",INDEX('📦 Registro'!$B$4:$B$103,MATCH(I61,'📦 Registro'!$A$4:$A$103,0))),"")} | C61: {=IFERROR(IF(I61="","",INDEX('📦 Registro'!$D$4:$D$103,MATCH(I61,'📦 Registro'!$A$4:$A$103,0))),"")} | D61: {=IFERROR(IF(I61="","",INDEX('📦 Registro'!$E$4:$E$103,MATCH(I61,'📦 Registro'!$A$4:$A$103,0))),"")} | E61: {=IFERROR(IF(I61="","",INDEX('📦 Registro'!$I$4:$I$103,MATCH(I61,'📦 Registro'!$A$4:$A$103,0))),"")} | F61: {=IFERROR(IF(I61="","",INDEX('📦 Registro'!$C$4:$C$103,MATCH(I61,'📦 Registro'!$A$4:$A$103,0))),"")} | G61: {=IFERROR(IF(I61="","",INDEX('📦 Registro'!$N$4:$N$103,MATCH(I61,'📦 Registro'!$A$4:$A$103,0))),"")} | H61: =IFERROR(IF(F61="","",TODAY()-F61),"") | I61: {=IFERROR(INDEX(#REF!,MATCH(SMALL(IF(#REF!<>"",ROW(#REF!)-3),58),#REF!,0)),"")}
A62: {=IFERROR(IF(I62="","",INDEX('📦 Registro'!$A$4:$A$103,MATCH(I62,'📦 Registro'!$A$4:$A$103,0))),"")} | B62: {=IFERROR(IF(I62="","",INDEX('📦 Registro'!$B$4:$B$103,MATCH(I62,'📦 Registro'!$A$4:$A$103,0))),"")} | C62: {=IFERROR(IF(I62="","",INDEX('📦 Registro'!$D$4:$D$103,MATCH(I62,'📦 Registro'!$A$4:$A$103,0))),"")} | D62: {=IFERROR(IF(I62="","",INDEX('📦 Registro'!$E$4:$E$103,MATCH(I62,'📦 Registro'!$A$4:$A$103,0))),"")} | E62: {=IFERROR(IF(I62="","",INDEX('📦 Registro'!$I$4:$I$103,MATCH(I62,'📦 Registro'!$A$4:$A$103,0))),"")} | F62: {=IFERROR(IF(I62="","",INDEX('📦 Registro'!$C$4:$C$103,MATCH(I62,'📦 Registro'!$A$4:$A$103,0))),"")} | G62: {=IFERROR(IF(I62="","",INDEX('📦 Registro'!$N$4:$N$103,MATCH(I62,'📦 Registro'!$A$4:$A$103,0))),"")} | H62: =IFERROR(IF(F62="","",TODAY()-F62),"") | I62: {=IFERROR(INDEX(#REF!,MATCH(SMALL(IF(#REF!<>"",ROW(#REF!)-3),59),#REF!,0)),"")}
A63: {=IFERROR(IF(I63="","",INDEX('📦 Registro'!$A$4:$A$103,MATCH(I63,'📦 Registro'!$A$4:$A$103,0))),"")} | B63: {=IFERROR(IF(I63="","",INDEX('📦 Registro'!$B$4:$B$103,MATCH(I63,'📦 Registro'!$A$4:$A$103,0))),"")} | C63: {=IFERROR(IF(I63="","",INDEX('📦 Registro'!$D$4:$D$103,MATCH(I63,'📦 Registro'!$A$4:$A$103,0))),"")} | D63: {=IFERROR(IF(I63="","",INDEX('📦 Registro'!$E$4:$E$103,MATCH(I63,'📦 Registro'!$A$4:$A$103,0))),"")} | E63: {=IFERROR(IF(I63="","",INDEX('📦 Registro'!$I$4:$I$103,MATCH(I63,'📦 Registro'!$A$4:$A$103,0))),"")} | F63: {=IFERROR(IF(I63="","",INDEX('📦 Registro'!$C$4:$C$103,MATCH(I63,'📦 Registro'!$A$4:$A$103,0))),"")} | G63: {=IFERROR(IF(I63="","",INDEX('📦 Registro'!$N$4:$N$103,MATCH(I63,'📦 Registro'!$A$4:$A$103,0))),"")} | H63: =IFERROR(IF(F63="","",TODAY()-F63),"") | I63: {=IFERROR(INDEX(#REF!,MATCH(SMALL(IF(#REF!<>"",ROW(#REF!)-3),60),#REF!,0)),"")}
A64: {=IFERROR(IF(I64="","",INDEX('📦 Registro'!$A$4:$A$103,MATCH(I64,'📦 Registro'!$A$4:$A$103,0))),"")} | B64: {=IFERROR(IF(I64="","",INDEX('📦 Registro'!$B$4:$B$103,MATCH(I64,'📦 Registro'!$A$4:$A$103,0))),"")} | C64: {=IFERROR(IF(I64="","",INDEX('📦 Registro'!$D$4:$D$103,MATCH(I64,'📦 Registro'!$A$4:$A$103,0))),"")} | D64: {=IFERROR(IF(I64="","",INDEX('📦 Registro'!$E$4:$E$103,MATCH(I64,'📦 Registro'!$A$4:$A$103,0))),"")} | E64: {=IFERROR(IF(I64="","",INDEX('📦 Registro'!$I$4:$I$103,MATCH(I64,'📦 Registro'!$A$4:$A$103,0))),"")} | F64: {=IFERROR(IF(I64="","",INDEX('📦 Registro'!$C$4:$C$103,MATCH(I64,'📦 Registro'!$A$4:$A$103,0))),"")} | G64: {=IFERROR(IF(I64="","",INDEX('📦 Registro'!$N$4:$N$103,MATCH(I64,'📦 Registro'!$A$4:$A$103,0))),"")} | H64: =IFERROR(IF(F64="","",TODAY()-F64),"") | I64: {=IFERROR(INDEX(#REF!,MATCH(SMALL(IF(#REF!<>"",ROW(#REF!)-3),61),#REF!,0)),"")}
A65: {=IFERROR(IF(I65="","",INDEX('📦 Registro'!$A$4:$A$103,MATCH(I65,'📦 Registro'!$A$4:$A$103,0))),"")} | B65: {=IFERROR(IF(I65="","",INDEX('📦 Registro'!$B$4:$B$103,MATCH(I65,'📦 Registro'!$A$4:$A$103,0))),"")} | C65: {=IFERROR(IF(I65="","",INDEX('📦 Registro'!$D$4:$D$103,MATCH(I65,'📦 Registro'!$A$4:$A$103,0))),"")} | D65: {=IFERROR(IF(I65="","",INDEX('📦 Registro'!$E$4:$E$103,MATCH(I65,'📦 Registro'!$A$4:$A$103,0))),"")} | E65: {=IFERROR(IF(I65="","",INDEX('📦 Registro'!$I$4:$I$103,MATCH(I65,'📦 Registro'!$A$4:$A$103,0))),"")} | F65: {=IFERROR(IF(I65="","",INDEX('📦 Registro'!$C$4:$C$103,MATCH(I65,'📦 Registro'!$A$4:$A$103,0))),"")} | G65: {=IFERROR(IF(I65="","",INDEX('📦 Registro'!$N$4:$N$103,MATCH(I65,'📦 Registro'!$A$4:$A$103,0))),"")} | H65: =IFERROR(IF(F65="","",TODAY()-F65),"") | I65: {=IFERROR(INDEX(#REF!,MATCH(SMALL(IF(#REF!<>"",ROW(#REF!)-3),62),#REF!,0)),"")}
A66: {=IFERROR(IF(I66="","",INDEX('📦 Registro'!$A$4:$A$103,MATCH(I66,'📦 Registro'!$A$4:$A$103,0))),"")} | B66: {=IFERROR(IF(I66="","",INDEX('📦 Registro'!$B$4:$B$103,MATCH(I66,'📦 Registro'!$A$4:$A$103,0))),"")} | C66: {=IFERROR(IF(I66="","",INDEX('📦 Registro'!$D$4:$D$103,MATCH(I66,'📦 Registro'!$A$4:$A$103,0))),"")} | D66: {=IFERROR(IF(I66="","",INDEX('📦 Registro'!$E$4:$E$103,MATCH(I66,'📦 Registro'!$A$4:$A$103,0))),"")} | E66: {=IFERROR(IF(I66="","",INDEX('📦 Registro'!$I$4:$I$103,MATCH(I66,'📦 Registro'!$A$4:$A$103,0))),"")} | F66: {=IFERROR(IF(I66="","",INDEX('📦 Registro'!$C$4:$C$103,MATCH(I66,'📦 Registro'!$A$4:$A$103,0))),"")} | G66: {=IFERROR(IF(I66="","",INDEX('📦 Registro'!$N$4:$N$103,MATCH(I66,'📦 Registro'!$A$4:$A$103,0))),"")} | H66: =IFERROR(IF(F66="","",TODAY()-F66),"") | I66: {=IFERROR(INDEX(#REF!,MATCH(SMALL(IF(#REF!<>"",ROW(#REF!)-3),63),#REF!,0)),"")}
A67: {=IFERROR(IF(I67="","",INDEX('📦 Registro'!$A$4:$A$103,MATCH(I67,'📦 Registro'!$A$4:$A$103,0))),"")} | B67: {=IFERROR(IF(I67="","",INDEX('📦 Registro'!$B$4:$B$103,MATCH(I67,'📦 Registro'!$A$4:$A$103,0))),"")} | C67: {=IFERROR(IF(I67="","",INDEX('📦 Registro'!$D$4:$D$103,MATCH(I67,'📦 Registro'!$A$4:$A$103,0))),"")} | D67: {=IFERROR(IF(I67="","",INDEX('📦 Registro'!$E$4:$E$103,MATCH(I67,'📦 Registro'!$A$4:$A$103,0))),"")} | E67: {=IFERROR(IF(I67="","",INDEX('📦 Registro'!$I$4:$I$103,MATCH(I67,'📦 Registro'!$A$4:$A$103,0))),"")} | F67: {=IFERROR(IF(I67="","",INDEX('📦 Registro'!$C$4:$C$103,MATCH(I67,'📦 Registro'!$A$4:$A$103,0))),"")} | G67: {=IFERROR(IF(I67="","",INDEX('📦 Registro'!$N$4:$N$103,MATCH(I67,'📦 Registro'!$A$4:$A$103,0))),"")} | H67: =IFERROR(IF(F67="","",TODAY()-F67),"") | I67: {=IFERROR(INDEX(#REF!,MATCH(SMALL(IF(#REF!<>"",ROW(#REF!)-3),64),#REF!,0)),"")}
A68: {=IFERROR(IF(I68="","",INDEX('📦 Registro'!$A$4:$A$103,MATCH(I68,'📦 Registro'!$A$4:$A$103,0))),"")} | B68: {=IFERROR(IF(I68="","",INDEX('📦 Registro'!$B$4:$B$103,MATCH(I68,'📦 Registro'!$A$4:$A$103,0))),"")} | C68: {=IFERROR(IF(I68="","",INDEX('📦 Registro'!$D$4:$D$103,MATCH(I68,'📦 Registro'!$A$4:$A$103,0))),"")} | D68: {=IFERROR(IF(I68="","",INDEX('📦 Registro'!$E$4:$E$103,MATCH(I68,'📦 Registro'!$A$4:$A$103,0))),"")} | E68: {=IFERROR(IF(I68="","",INDEX('📦 Registro'!$I$4:$I$103,MATCH(I68,'📦 Registro'!$A$4:$A$103,0))),"")} | F68: {=IFERROR(IF(I68="","",INDEX('📦 Registro'!$C$4:$C$103,MATCH(I68,'📦 Registro'!$A$4:$A$103,0))),"")} | G68: {=IFERROR(IF(I68="","",INDEX('📦 Registro'!$N$4:$N$103,MATCH(I68,'📦 Registro'!$A$4:$A$103,0))),"")} | H68: =IFERROR(IF(F68="","",TODAY()-F68),"") | I68: {=IFERROR(INDEX(#REF!,MATCH(SMALL(IF(#REF!<>"",ROW(#REF!)-3),65),#REF!,0)),"")}
A69: {=IFERROR(IF(I69="","",INDEX('📦 Registro'!$A$4:$A$103,MATCH(I69,'📦 Registro'!$A$4:$A$103,0))),"")} | B69: {=IFERROR(IF(I69="","",INDEX('📦 Registro'!$B$4:$B$103,MATCH(I69,'📦 Registro'!$A$4:$A$103,0))),"")} | C69: {=IFERROR(IF(I69="","",INDEX('📦 Registro'!$D$4:$D$103,MATCH(I69,'📦 Registro'!$A$4:$A$103,0))),"")} | D69: {=IFERROR(IF(I69="","",INDEX('📦 Registro'!$E$4:$E$103,MATCH(I69,'📦 Registro'!$A$4:$A$103,0))),"")} | E69: {=IFERROR(IF(I69="","",INDEX('📦 Registro'!$I$4:$I$103,MATCH(I69,'📦 Registro'!$A$4:$A$103,0))),"")} | F69: {=IFERROR(IF(I69="","",INDEX('📦 Registro'!$C$4:$C$103,MATCH(I69,'📦 Registro'!$A$4:$A$103,0))),"")} | G69: {=IFERROR(IF(I69="","",INDEX('📦 Registro'!$N$4:$N$103,MATCH(I69,'📦 Registro'!$A$4:$A$103,0))),"")} | H69: =IFERROR(IF(F69="","",TODAY()-F69),"") | I69: {=IFERROR(INDEX(#REF!,MATCH(SMALL(IF(#REF!<>"",ROW(#REF!)-3),66),#REF!,0)),"")}
A70: {=IFERROR(IF(I70="","",INDEX('📦 Registro'!$A$4:$A$103,MATCH(I70,'📦 Registro'!$A$4:$A$103,0))),"")} | B70: {=IFERROR(IF(I70="","",INDEX('📦 Registro'!$B$4:$B$103,MATCH(I70,'📦 Registro'!$A$4:$A$103,0))),"")} | C70: {=IFERROR(IF(I70="","",INDEX('📦 Registro'!$D$4:$D$103,MATCH(I70,'📦 Registro'!$A$4:$A$103,0))),"")} | D70: {=IFERROR(IF(I70="","",INDEX('📦 Registro'!$E$4:$E$103,MATCH(I70,'📦 Registro'!$A$4:$A$103,0))),"")} | E70: {=IFERROR(IF(I70="","",INDEX('📦 Registro'!$I$4:$I$103,MATCH(I70,'📦 Registro'!$A$4:$A$103,0))),"")} | F70: {=IFERROR(IF(I70="","",INDEX('📦 Registro'!$C$4:$C$103,MATCH(I70,'📦 Registro'!$A$4:$A$103,0))),"")} | G70: {=IFERROR(IF(I70="","",INDEX('📦 Registro'!$N$4:$N$103,MATCH(I70,'📦 Registro'!$A$4:$A$103,0))),"")} | H70: =IFERROR(IF(F70="","",TODAY()-F70),"") | I70: {=IFERROR(INDEX(#REF!,MATCH(SMALL(IF(#REF!<>"",ROW(#REF!)-3),67),#REF!,0)),"")}
A71: {=IFERROR(IF(I71="","",INDEX('📦 Registro'!$A$4:$A$103,MATCH(I71,'📦 Registro'!$A$4:$A$103,0))),"")} | B71: {=IFERROR(IF(I71="","",INDEX('📦 Registro'!$B$4:$B$103,MATCH(I71,'📦 Registro'!$A$4:$A$103,0))),"")} | C71: {=IFERROR(IF(I71="","",INDEX('📦 Registro'!$D$4:$D$103,MATCH(I71,'📦 Registro'!$A$4:$A$103,0))),"")} | D71: {=IFERROR(IF(I71="","",INDEX('📦 Registro'!$E$4:$E$103,MATCH(I71,'📦 Registro'!$A$4:$A$103,0))),"")} | E71: {=IFERROR(IF(I71="","",INDEX('📦 Registro'!$I$4:$I$103,MATCH(I71,'📦 Registro'!$A$4:$A$103,0))),"")} | F71: {=IFERROR(IF(I71="","",INDEX('📦 Registro'!$C$4:$C$103,MATCH(I71,'📦 Registro'!$A$4:$A$103,0))),"")} | G71: {=IFERROR(IF(I71="","",INDEX('📦 Registro'!$N$4:$N$103,MATCH(I71,'📦 Registro'!$A$4:$A$103,0))),"")} | H71: =IFERROR(IF(F71="","",TODAY()-F71),"") | I71: {=IFERROR(INDEX(#REF!,MATCH(SMALL(IF(#REF!<>"",ROW(#REF!)-3),68),#REF!,0)),"")}
A72: {=IFERROR(IF(I72="","",INDEX('📦 Registro'!$A$4:$A$103,MATCH(I72,'📦 Registro'!$A$4:$A$103,0))),"")} | B72: {=IFERROR(IF(I72="","",INDEX('📦 Registro'!$B$4:$B$103,MATCH(I72,'📦 Registro'!$A$4:$A$103,0))),"")} | C72: {=IFERROR(IF(I72="","",INDEX('📦 Registro'!$D$4:$D$103,MATCH(I72,'📦 Registro'!$A$4:$A$103,0))),"")} | D72: {=IFERROR(IF(I72="","",INDEX('📦 Registro'!$E$4:$E$103,MATCH(I72,'📦 Registro'!$A$4:$A$103,0))),"")} | E72: {=IFERROR(IF(I72="","",INDEX('📦 Registro'!$I$4:$I$103,MATCH(I72,'📦 Registro'!$A$4:$A$103,0))),"")} | F72: {=IFERROR(IF(I72="","",INDEX('📦 Registro'!$C$4:$C$103,MATCH(I72,'📦 Registro'!$A$4:$A$103,0))),"")} | G72: {=IFERROR(IF(I72="","",INDEX('📦 Registro'!$N$4:$N$103,MATCH(I72,'📦 Registro'!$A$4:$A$103,0))),"")} | H72: =IFERROR(IF(F72="","",TODAY()-F72),"") | I72: {=IFERROR(INDEX(#REF!,MATCH(SMALL(IF(#REF!<>"",ROW(#REF!)-3),69),#REF!,0)),"")}
A73: {=IFERROR(IF(I73="","",INDEX('📦 Registro'!$A$4:$A$103,MATCH(I73,'📦 Registro'!$A$4:$A$103,0))),"")} | B73: {=IFERROR(IF(I73="","",INDEX('📦 Registro'!$B$4:$B$103,MATCH(I73,'📦 Registro'!$A$4:$A$103,0))),"")} | C73: {=IFERROR(IF(I73="","",INDEX('📦 Registro'!$D$4:$D$103,MATCH(I73,'📦 Registro'!$A$4:$A$103,0))),"")} | D73: {=IFERROR(IF(I73="","",INDEX('📦 Registro'!$E$4:$E$103,MATCH(I73,'📦 Registro'!$A$4:$A$103,0))),"")} | E73: {=IFERROR(IF(I73="","",INDEX('📦 Registro'!$I$4:$I$103,MATCH(I73,'📦 Registro'!$A$4:$A$103,0))),"")} | F73: {=IFERROR(IF(I73="","",INDEX('📦 Registro'!$C$4:$C$103,MATCH(I73,'📦 Registro'!$A$4:$A$103,0))),"")} | G73: {=IFERROR(IF(I73="","",INDEX('📦 Registro'!$N$4:$N$103,MATCH(I73,'📦 Registro'!$A$4:$A$103,0))),"")} | H73: =IFERROR(IF(F73="","",TODAY()-F73),"") | I73: {=IFERROR(INDEX(#REF!,MATCH(SMALL(IF(#REF!<>"",ROW(#REF!)-3),70),#REF!,0)),"")}
A74: {=IFERROR(IF(I74="","",INDEX('📦 Registro'!$A$4:$A$103,MATCH(I74,'📦 Registro'!$A$4:$A$103,0))),"")} | B74: {=IFERROR(IF(I74="","",INDEX('📦 Registro'!$B$4:$B$103,MATCH(I74,'📦 Registro'!$A$4:$A$103,0))),"")} | C74: {=IFERROR(IF(I74="","",INDEX('📦 Registro'!$D$4:$D$103,MATCH(I74,'📦 Registro'!$A$4:$A$103,0))),"")} | D74: {=IFERROR(IF(I74="","",INDEX('📦 Registro'!$E$4:$E$103,MATCH(I74,'📦 Registro'!$A$4:$A$103,0))),"")} | E74: {=IFERROR(IF(I74="","",INDEX('📦 Registro'!$I$4:$I$103,MATCH(I74,'📦 Registro'!$A$4:$A$103,0))),"")} | F74: {=IFERROR(IF(I74="","",INDEX('📦 Registro'!$C$4:$C$103,MATCH(I74,'📦 Registro'!$A$4:$A$103,0))),"")} | G74: {=IFERROR(IF(I74="","",INDEX('📦 Registro'!$N$4:$N$103,MATCH(I74,'📦 Registro'!$A$4:$A$103,0))),"")} | H74: =IFERROR(IF(F74="","",TODAY()-F74),"") | I74: {=IFERROR(INDEX(#REF!,MATCH(SMALL(IF(#REF!<>"",ROW(#REF!)-3),71),#REF!,0)),"")}
A75: {=IFERROR(IF(I75="","",INDEX('📦 Registro'!$A$4:$A$103,MATCH(I75,'📦 Registro'!$A$4:$A$103,0))),"")} | B75: {=IFERROR(IF(I75="","",INDEX('📦 Registro'!$B$4:$B$103,MATCH(I75,'📦 Registro'!$A$4:$A$103,0))),"")} | C75: {=IFERROR(IF(I75="","",INDEX('📦 Registro'!$D$4:$D$103,MATCH(I75,'📦 Registro'!$A$4:$A$103,0))),"")} | D75: {=IFERROR(IF(I75="","",INDEX('📦 Registro'!$E$4:$E$103,MATCH(I75,'📦 Registro'!$A$4:$A$103,0))),"")} | E75: {=IFERROR(IF(I75="","",INDEX('📦 Registro'!$I$4:$I$103,MATCH(I75,'📦 Registro'!$A$4:$A$103,0))),"")} | F75: {=IFERROR(IF(I75="","",INDEX('📦 Registro'!$C$4:$C$103,MATCH(I75,'📦 Registro'!$A$4:$A$103,0))),"")} | G75: {=IFERROR(IF(I75="","",INDEX('📦 Registro'!$N$4:$N$103,MATCH(I75,'📦 Registro'!$A$4:$A$103,0))),"")} | H75: =IFERROR(IF(F75="","",TODAY()-F75),"") | I75: {=IFERROR(INDEX(#REF!,MATCH(SMALL(IF(#REF!<>"",ROW(#REF!)-3),72),#REF!,0)),"")}
A76: {=IFERROR(IF(I76="","",INDEX('📦 Registro'!$A$4:$A$103,MATCH(I76,'📦 Registro'!$A$4:$A$103,0))),"")} | B76: {=IFERROR(IF(I76="","",INDEX('📦 Registro'!$B$4:$B$103,MATCH(I76,'📦 Registro'!$A$4:$A$103,0))),"")} | C76: {=IFERROR(IF(I76="","",INDEX('📦 Registro'!$D$4:$D$103,MATCH(I76,'📦 Registro'!$A$4:$A$103,0))),"")} | D76: {=IFERROR(IF(I76="","",INDEX('📦 Registro'!$E$4:$E$103,MATCH(I76,'📦 Registro'!$A$4:$A$103,0))),"")} | E76: {=IFERROR(IF(I76="","",INDEX('📦 Registro'!$I$4:$I$103,MATCH(I76,'📦 Registro'!$A$4:$A$103,0))),"")} | F76: {=IFERROR(IF(I76="","",INDEX('📦 Registro'!$C$4:$C$103,MATCH(I76,'📦 Registro'!$A$4:$A$103,0))),"")} | G76: {=IFERROR(IF(I76="","",INDEX('📦 Registro'!$N$4:$N$103,MATCH(I76,'📦 Registro'!$A$4:$A$103,0))),"")} | H76: =IFERROR(IF(F76="","",TODAY()-F76),"") | I76: {=IFERROR(INDEX(#REF!,MATCH(SMALL(IF(#REF!<>"",ROW(#REF!)-3),73),#REF!,0)),"")}
A77: {=IFERROR(IF(I77="","",INDEX('📦 Registro'!$A$4:$A$103,MATCH(I77,'📦 Registro'!$A$4:$A$103,0))),"")} | B77: {=IFERROR(IF(I77="","",INDEX('📦 Registro'!$B$4:$B$103,MATCH(I77,'📦 Registro'!$A$4:$A$103,0))),"")} | C77: {=IFERROR(IF(I77="","",INDEX('📦 Registro'!$D$4:$D$103,MATCH(I77,'📦 Registro'!$A$4:$A$103,0))),"")} | D77: {=IFERROR(IF(I77="","",INDEX('📦 Registro'!$E$4:$E$103,MATCH(I77,'📦 Registro'!$A$4:$A$103,0))),"")} | E77: {=IFERROR(IF(I77="","",INDEX('📦 Registro'!$I$4:$I$103,MATCH(I77,'📦 Registro'!$A$4:$A$103,0))),"")} | F77: {=IFERROR(IF(I77="","",INDEX('📦 Registro'!$C$4:$C$103,MATCH(I77,'📦 Registro'!$A$4:$A$103,0))),"")} | G77: {=IFERROR(IF(I77="","",INDEX('📦 Registro'!$N$4:$N$103,MATCH(I77,'📦 Registro'!$A$4:$A$103,0))),"")} | H77: =IFERROR(IF(F77="","",TODAY()-F77),"") | I77: {=IFERROR(INDEX(#REF!,MATCH(SMALL(IF(#REF!<>"",ROW(#REF!)-3),74),#REF!,0)),"")}
A78: {=IFERROR(IF(I78="","",INDEX('📦 Registro'!$A$4:$A$103,MATCH(I78,'📦 Registro'!$A$4:$A$103,0))),"")} | B78: {=IFERROR(IF(I78="","",INDEX('📦 Registro'!$B$4:$B$103,MATCH(I78,'📦 Registro'!$A$4:$A$103,0))),"")} | C78: {=IFERROR(IF(I78="","",INDEX('📦 Registro'!$D$4:$D$103,MATCH(I78,'📦 Registro'!$A$4:$A$103,0))),"")} | D78: {=IFERROR(IF(I78="","",INDEX('📦 Registro'!$E$4:$E$103,MATCH(I78,'📦 Registro'!$A$4:$A$103,0))),"")} | E78: {=IFERROR(IF(I78="","",INDEX('📦 Registro'!$I$4:$I$103,MATCH(I78,'📦 Registro'!$A$4:$A$103,0))),"")} | F78: {=IFERROR(IF(I78="","",INDEX('📦 Registro'!$C$4:$C$103,MATCH(I78,'📦 Registro'!$A$4:$A$103,0))),"")} | G78: {=IFERROR(IF(I78="","",INDEX('📦 Registro'!$N$4:$N$103,MATCH(I78,'📦 Registro'!$A$4:$A$103,0))),"")} | H78: =IFERROR(IF(F78="","",TODAY()-F78),"") | I78: {=IFERROR(INDEX(#REF!,MATCH(SMALL(IF(#REF!<>"",ROW(#REF!)-3),75),#REF!,0)),"")}
A79: {=IFERROR(IF(I79="","",INDEX('📦 Registro'!$A$4:$A$103,MATCH(I79,'📦 Registro'!$A$4:$A$103,0))),"")} | B79: {=IFERROR(IF(I79="","",INDEX('📦 Registro'!$B$4:$B$103,MATCH(I79,'📦 Registro'!$A$4:$A$103,0))),"")} | C79: {=IFERROR(IF(I79="","",INDEX('📦 Registro'!$D$4:$D$103,MATCH(I79,'📦 Registro'!$A$4:$A$103,0))),"")} | D79: {=IFERROR(IF(I79="","",INDEX('📦 Registro'!$E$4:$E$103,MATCH(I79,'📦 Registro'!$A$4:$A$103,0))),"")} | E79: {=IFERROR(IF(I79="","",INDEX('📦 Registro'!$I$4:$I$103,MATCH(I79,'📦 Registro'!$A$4:$A$103,0))),"")} | F79: {=IFERROR(IF(I79="","",INDEX('📦 Registro'!$C$4:$C$103,MATCH(I79,'📦 Registro'!$A$4:$A$103,0))),"")} | G79: {=IFERROR(IF(I79="","",INDEX('📦 Registro'!$N$4:$N$103,MATCH(I79,'📦 Registro'!$A$4:$A$103,0))),"")} | H79: =IFERROR(IF(F79="","",TODAY()-F79),"") | I79: {=IFERROR(INDEX(#REF!,MATCH(SMALL(IF(#REF!<>"",ROW(#REF!)-3),76),#REF!,0)),"")}
A80: {=IFERROR(IF(I80="","",INDEX('📦 Registro'!$A$4:$A$103,MATCH(I80,'📦 Registro'!$A$4:$A$103,0))),"")} | B80: {=IFERROR(IF(I80="","",INDEX('📦 Registro'!$B$4:$B$103,MATCH(I80,'📦 Registro'!$A$4:$A$103,0))),"")} | C80: {=IFERROR(IF(I80="","",INDEX('📦 Registro'!$D$4:$D$103,MATCH(I80,'📦 Registro'!$A$4:$A$103,0))),"")} | D80: {=IFERROR(IF(I80="","",INDEX('📦 Registro'!$E$4:$E$103,MATCH(I80,'📦 Registro'!$A$4:$A$103,0))),"")} | E80: {=IFERROR(IF(I80="","",INDEX('📦 Registro'!$I$4:$I$103,MATCH(I80,'📦 Registro'!$A$4:$A$103,0))),"")} | F80: {=IFERROR(IF(I80="","",INDEX('📦 Registro'!$C$4:$C$103,MATCH(I80,'📦 Registro'!$A$4:$A$103,0))),"")} | G80: {=IFERROR(IF(I80="","",INDEX('📦 Registro'!$N$4:$N$103,MATCH(I80,'📦 Registro'!$A$4:$A$103,0))),"")} | H80: =IFERROR(IF(F80="","",TODAY()-F80),"") | I80: {=IFERROR(INDEX(#REF!,MATCH(SMALL(IF(#REF!<>"",ROW(#REF!)-3),77),#REF!,0)),"")}
A81: {=IFERROR(IF(I81="","",INDEX('📦 Registro'!$A$4:$A$103,MATCH(I81,'📦 Registro'!$A$4:$A$103,0))),"")} | B81: {=IFERROR(IF(I81="","",INDEX('📦 Registro'!$B$4:$B$103,MATCH(I81,'📦 Registro'!$A$4:$A$103,0))),"")} | C81: {=IFERROR(IF(I81="","",INDEX('📦 Registro'!$D$4:$D$103,MATCH(I81,'📦 Registro'!$A$4:$A$103,0))),"")} | D81: {=IFERROR(IF(I81="","",INDEX('📦 Registro'!$E$4:$E$103,MATCH(I81,'📦 Registro'!$A$4:$A$103,0))),"")} | E81: {=IFERROR(IF(I81="","",INDEX('📦 Registro'!$I$4:$I$103,MATCH(I81,'📦 Registro'!$A$4:$A$103,0))),"")} | F81: {=IFERROR(IF(I81="","",INDEX('📦 Registro'!$C$4:$C$103,MATCH(I81,'📦 Registro'!$A$4:$A$103,0))),"")} | G81: {=IFERROR(IF(I81="","",INDEX('📦 Registro'!$N$4:$N$103,MATCH(I81,'📦 Registro'!$A$4:$A$103,0))),"")} | H81: =IFERROR(IF(F81="","",TODAY()-F81),"") | I81: {=IFERROR(INDEX(#REF!,MATCH(SMALL(IF(#REF!<>"",ROW(#REF!)-3),78),#REF!,0)),"")}
A82: {=IFERROR(IF(I82="","",INDEX('📦 Registro'!$A$4:$A$103,MATCH(I82,'📦 Registro'!$A$4:$A$103,0))),"")} | B82: {=IFERROR(IF(I82="","",INDEX('📦 Registro'!$B$4:$B$103,MATCH(I82,'📦 Registro'!$A$4:$A$103,0))),"")} | C82: {=IFERROR(IF(I82="","",INDEX('📦 Registro'!$D$4:$D$103,MATCH(I82,'📦 Registro'!$A$4:$A$103,0))),"")} | D82: {=IFERROR(IF(I82="","",INDEX('📦 Registro'!$E$4:$E$103,MATCH(I82,'📦 Registro'!$A$4:$A$103,0))),"")} | E82: {=IFERROR(IF(I82="","",INDEX('📦 Registro'!$I$4:$I$103,MATCH(I82,'📦 Registro'!$A$4:$A$103,0))),"")} | F82: {=IFERROR(IF(I82="","",INDEX('📦 Registro'!$C$4:$C$103,MATCH(I82,'📦 Registro'!$A$4:$A$103,0))),"")} | G82: {=IFERROR(IF(I82="","",INDEX('📦 Registro'!$N$4:$N$103,MATCH(I82,'📦 Registro'!$A$4:$A$103,0))),"")} | H82: =IFERROR(IF(F82="","",TODAY()-F82),"") | I82: {=IFERROR(INDEX(#REF!,MATCH(SMALL(IF(#REF!<>"",ROW(#REF!)-3),79),#REF!,0)),"")}
A83: {=IFERROR(IF(I83="","",INDEX('📦 Registro'!$A$4:$A$103,MATCH(I83,'📦 Registro'!$A$4:$A$103,0))),"")} | B83: {=IFERROR(IF(I83="","",INDEX('📦 Registro'!$B$4:$B$103,MATCH(I83,'📦 Registro'!$A$4:$A$103,0))),"")} | C83: {=IFERROR(IF(I83="","",INDEX('📦 Registro'!$D$4:$D$103,MATCH(I83,'📦 Registro'!$A$4:$A$103,0))),"")} | D83: {=IFERROR(IF(I83="","",INDEX('📦 Registro'!$E$4:$E$103,MATCH(I83,'📦 Registro'!$A$4:$A$103,0))),"")} | E83: {=IFERROR(IF(I83="","",INDEX('📦 Registro'!$I$4:$I$103,MATCH(I83,'📦 Registro'!$A$4:$A$103,0))),"")} | F83: {=IFERROR(IF(I83="","",INDEX('📦 Registro'!$C$4:$C$103,MATCH(I83,'📦 Registro'!$A$4:$A$103,0))),"")} | G83: {=IFERROR(IF(I83="","",INDEX('📦 Registro'!$N$4:$N$103,MATCH(I83,'📦 Registro'!$A$4:$A$103,0))),"")} | H83: =IFERROR(IF(F83="","",TODAY()-F83),"") | I83: {=IFERROR(INDEX(#REF!,MATCH(SMALL(IF(#REF!<>"",ROW(#REF!)-3),80),#REF!,0)),"")}
A84: {=IFERROR(IF(I84="","",INDEX('📦 Registro'!$A$4:$A$103,MATCH(I84,'📦 Registro'!$A$4:$A$103,0))),"")} | B84: {=IFERROR(IF(I84="","",INDEX('📦 Registro'!$B$4:$B$103,MATCH(I84,'📦 Registro'!$A$4:$A$103,0))),"")} | C84: {=IFERROR(IF(I84="","",INDEX('📦 Registro'!$D$4:$D$103,MATCH(I84,'📦 Registro'!$A$4:$A$103,0))),"")} | D84: {=IFERROR(IF(I84="","",INDEX('📦 Registro'!$E$4:$E$103,MATCH(I84,'📦 Registro'!$A$4:$A$103,0))),"")} | E84: {=IFERROR(IF(I84="","",INDEX('📦 Registro'!$I$4:$I$103,MATCH(I84,'📦 Registro'!$A$4:$A$103,0))),"")} | F84: {=IFERROR(IF(I84="","",INDEX('📦 Registro'!$C$4:$C$103,MATCH(I84,'📦 Registro'!$A$4:$A$103,0))),"")} | G84: {=IFERROR(IF(I84="","",INDEX('📦 Registro'!$N$4:$N$103,MATCH(I84,'📦 Registro'!$A$4:$A$103,0))),"")} | H84: =IFERROR(IF(F84="","",TODAY()-F84),"") | I84: {=IFERROR(INDEX(#REF!,MATCH(SMALL(IF(#REF!<>"",ROW(#REF!)-3),81),#REF!,0)),"")}
A85: {=IFERROR(IF(I85="","",INDEX('📦 Registro'!$A$4:$A$103,MATCH(I85,'📦 Registro'!$A$4:$A$103,0))),"")} | B85: {=IFERROR(IF(I85="","",INDEX('📦 Registro'!$B$4:$B$103,MATCH(I85,'📦 Registro'!$A$4:$A$103,0))),"")} | C85: {=IFERROR(IF(I85="","",INDEX('📦 Registro'!$D$4:$D$103,MATCH(I85,'📦 Registro'!$A$4:$A$103,0))),"")} | D85: {=IFERROR(IF(I85="","",INDEX('📦 Registro'!$E$4:$E$103,MATCH(I85,'📦 Registro'!$A$4:$A$103,0))),"")} | E85: {=IFERROR(IF(I85="","",INDEX('📦 Registro'!$I$4:$I$103,MATCH(I85,'📦 Registro'!$A$4:$A$103,0))),"")} | F85: {=IFERROR(IF(I85="","",INDEX('📦 Registro'!$C$4:$C$103,MATCH(I85,'📦 Registro'!$A$4:$A$103,0))),"")} | G85: {=IFERROR(IF(I85="","",INDEX('📦 Registro'!$N$4:$N$103,MATCH(I85,'📦 Registro'!$A$4:$A$103,0))),"")} | H85: =IFERROR(IF(F85="","",TODAY()-F85),"") | I85: {=IFERROR(INDEX(#REF!,MATCH(SMALL(IF(#REF!<>"",ROW(#REF!)-3),82),#REF!,0)),"")}
A86: {=IFERROR(IF(I86="","",INDEX('📦 Registro'!$A$4:$A$103,MATCH(I86,'📦 Registro'!$A$4:$A$103,0))),"")} | B86: {=IFERROR(IF(I86="","",INDEX('📦 Registro'!$B$4:$B$103,MATCH(I86,'📦 Registro'!$A$4:$A$103,0))),"")} | C86: {=IFERROR(IF(I86="","",INDEX('📦 Registro'!$D$4:$D$103,MATCH(I86,'📦 Registro'!$A$4:$A$103,0))),"")} | D86: {=IFERROR(IF(I86="","",INDEX('📦 Registro'!$E$4:$E$103,MATCH(I86,'📦 Registro'!$A$4:$A$103,0))),"")} | E86: {=IFERROR(IF(I86="","",INDEX('📦 Registro'!$I$4:$I$103,MATCH(I86,'📦 Registro'!$A$4:$A$103,0))),"")} | F86: {=IFERROR(IF(I86="","",INDEX('📦 Registro'!$C$4:$C$103,MATCH(I86,'📦 Registro'!$A$4:$A$103,0))),"")} | G86: {=IFERROR(IF(I86="","",INDEX('📦 Registro'!$N$4:$N$103,MATCH(I86,'📦 Registro'!$A$4:$A$103,0))),"")} | H86: =IFERROR(IF(F86="","",TODAY()-F86),"") | I86: {=IFERROR(INDEX(#REF!,MATCH(SMALL(IF(#REF!<>"",ROW(#REF!)-3),83),#REF!,0)),"")}
A87: {=IFERROR(IF(I87="","",INDEX('📦 Registro'!$A$4:$A$103,MATCH(I87,'📦 Registro'!$A$4:$A$103,0))),"")} | B87: {=IFERROR(IF(I87="","",INDEX('📦 Registro'!$B$4:$B$103,MATCH(I87,'📦 Registro'!$A$4:$A$103,0))),"")} | C87: {=IFERROR(IF(I87="","",INDEX('📦 Registro'!$D$4:$D$103,MATCH(I87,'📦 Registro'!$A$4:$A$103,0))),"")} | D87: {=IFERROR(IF(I87="","",INDEX('📦 Registro'!$E$4:$E$103,MATCH(I87,'📦 Registro'!$A$4:$A$103,0))),"")} | E87: {=IFERROR(IF(I87="","",INDEX('📦 Registro'!$I$4:$I$103,MATCH(I87,'📦 Registro'!$A$4:$A$103,0))),"")} | F87: {=IFERROR(IF(I87="","",INDEX('📦 Registro'!$C$4:$C$103,MATCH(I87,'📦 Registro'!$A$4:$A$103,0))),"")} | G87: {=IFERROR(IF(I87="","",INDEX('📦 Registro'!$N$4:$N$103,MATCH(I87,'📦 Registro'!$A$4:$A$103,0))),"")} | H87: =IFERROR(IF(F87="","",TODAY()-F87),"") | I87: {=IFERROR(INDEX(#REF!,MATCH(SMALL(IF(#REF!<>"",ROW(#REF!)-3),84),#REF!,0)),"")}
A88: {=IFERROR(IF(I88="","",INDEX('📦 Registro'!$A$4:$A$103,MATCH(I88,'📦 Registro'!$A$4:$A$103,0))),"")} | B88: {=IFERROR(IF(I88="","",INDEX('📦 Registro'!$B$4:$B$103,MATCH(I88,'📦 Registro'!$A$4:$A$103,0))),"")} | C88: {=IFERROR(IF(I88="","",INDEX('📦 Registro'!$D$4:$D$103,MATCH(I88,'📦 Registro'!$A$4:$A$103,0))),"")} | D88: {=IFERROR(IF(I88="","",INDEX('📦 Registro'!$E$4:$E$103,MATCH(I88,'📦 Registro'!$A$4:$A$103,0))),"")} | E88: {=IFERROR(IF(I88="","",INDEX('📦 Registro'!$I$4:$I$103,MATCH(I88,'📦 Registro'!$A$4:$A$103,0))),"")} | F88: {=IFERROR(IF(I88="","",INDEX('📦 Registro'!$C$4:$C$103,MATCH(I88,'📦 Registro'!$A$4:$A$103,0))),"")} | G88: {=IFERROR(IF(I88="","",INDEX('📦 Registro'!$N$4:$N$103,MATCH(I88,'📦 Registro'!$A$4:$A$103,0))),"")} | H88: =IFERROR(IF(F88="","",TODAY()-F88),"") | I88: {=IFERROR(INDEX(#REF!,MATCH(SMALL(IF(#REF!<>"",ROW(#REF!)-3),85),#REF!,0)),"")}
A89: {=IFERROR(IF(I89="","",INDEX('📦 Registro'!$A$4:$A$103,MATCH(I89,'📦 Registro'!$A$4:$A$103,0))),"")} | B89: {=IFERROR(IF(I89="","",INDEX('📦 Registro'!$B$4:$B$103,MATCH(I89,'📦 Registro'!$A$4:$A$103,0))),"")} | C89: {=IFERROR(IF(I89="","",INDEX('📦 Registro'!$D$4:$D$103,MATCH(I89,'📦 Registro'!$A$4:$A$103,0))),"")} | D89: {=IFERROR(IF(I89="","",INDEX('📦 Registro'!$E$4:$E$103,MATCH(I89,'📦 Registro'!$A$4:$A$103,0))),"")} | E89: {=IFERROR(IF(I89="","",INDEX('📦 Registro'!$I$4:$I$103,MATCH(I89,'📦 Registro'!$A$4:$A$103,0))),"")} | F89: {=IFERROR(IF(I89="","",INDEX('📦 Registro'!$C$4:$C$103,MATCH(I89,'📦 Registro'!$A$4:$A$103,0))),"")} | G89: {=IFERROR(IF(I89="","",INDEX('📦 Registro'!$N$4:$N$103,MATCH(I89,'📦 Registro'!$A$4:$A$103,0))),"")} | H89: =IFERROR(IF(F89="","",TODAY()-F89),"") | I89: {=IFERROR(INDEX(#REF!,MATCH(SMALL(IF(#REF!<>"",ROW(#REF!)-3),86),#REF!,0)),"")}
A90: {=IFERROR(IF(I90="","",INDEX('📦 Registro'!$A$4:$A$103,MATCH(I90,'📦 Registro'!$A$4:$A$103,0))),"")} | B90: {=IFERROR(IF(I90="","",INDEX('📦 Registro'!$B$4:$B$103,MATCH(I90,'📦 Registro'!$A$4:$A$103,0))),"")} | C90: {=IFERROR(IF(I90="","",INDEX('📦 Registro'!$D$4:$D$103,MATCH(I90,'📦 Registro'!$A$4:$A$103,0))),"")} | D90: {=IFERROR(IF(I90="","",INDEX('📦 Registro'!$E$4:$E$103,MATCH(I90,'📦 Registro'!$A$4:$A$103,0))),"")} | E90: {=IFERROR(IF(I90="","",INDEX('📦 Registro'!$I$4:$I$103,MATCH(I90,'📦 Registro'!$A$4:$A$103,0))),"")} | F90: {=IFERROR(IF(I90="","",INDEX('📦 Registro'!$C$4:$C$103,MATCH(I90,'📦 Registro'!$A$4:$A$103,0))),"")} | G90: {=IFERROR(IF(I90="","",INDEX('📦 Registro'!$N$4:$N$103,MATCH(I90,'📦 Registro'!$A$4:$A$103,0))),"")} | H90: =IFERROR(IF(F90="","",TODAY()-F90),"") | I90: {=IFERROR(INDEX(#REF!,MATCH(SMALL(IF(#REF!<>"",ROW(#REF!)-3),87),#REF!,0)),"")}
A91: {=IFERROR(IF(I91="","",INDEX('📦 Registro'!$A$4:$A$103,MATCH(I91,'📦 Registro'!$A$4:$A$103,0))),"")} | B91: {=IFERROR(IF(I91="","",INDEX('📦 Registro'!$B$4:$B$103,MATCH(I91,'📦 Registro'!$A$4:$A$103,0))),"")} | C91: {=IFERROR(IF(I91="","",INDEX('📦 Registro'!$D$4:$D$103,MATCH(I91,'📦 Registro'!$A$4:$A$103,0))),"")} | D91: {=IFERROR(IF(I91="","",INDEX('📦 Registro'!$E$4:$E$103,MATCH(I91,'📦 Registro'!$A$4:$A$103,0))),"")} | E91: {=IFERROR(IF(I91="","",INDEX('📦 Registro'!$I$4:$I$103,MATCH(I91,'📦 Registro'!$A$4:$A$103,0))),"")} | F91: {=IFERROR(IF(I91="","",INDEX('📦 Registro'!$C$4:$C$103,MATCH(I91,'📦 Registro'!$A$4:$A$103,0))),"")} | G91: {=IFERROR(IF(I91="","",INDEX('📦 Registro'!$N$4:$N$103,MATCH(I91,'📦 Registro'!$A$4:$A$103,0))),"")} | H91: =IFERROR(IF(F91="","",TODAY()-F91),"") | I91: {=IFERROR(INDEX(#REF!,MATCH(SMALL(IF(#REF!<>"",ROW(#REF!)-3),88),#REF!,0)),"")}
A92: {=IFERROR(IF(I92="","",INDEX('📦 Registro'!$A$4:$A$103,MATCH(I92,'📦 Registro'!$A$4:$A$103,0))),"")} | B92: {=IFERROR(IF(I92="","",INDEX('📦 Registro'!$B$4:$B$103,MATCH(I92,'📦 Registro'!$A$4:$A$103,0))),"")} | C92: {=IFERROR(IF(I92="","",INDEX('📦 Registro'!$D$4:$D$103,MATCH(I92,'📦 Registro'!$A$4:$A$103,0))),"")} | D92: {=IFERROR(IF(I92="","",INDEX('📦 Registro'!$E$4:$E$103,MATCH(I92,'📦 Registro'!$A$4:$A$103,0))),"")} | E92: {=IFERROR(IF(I92="","",INDEX('📦 Registro'!$I$4:$I$103,MATCH(I92,'📦 Registro'!$A$4:$A$103,0))),"")} | F92: {=IFERROR(IF(I92="","",INDEX('📦 Registro'!$C$4:$C$103,MATCH(I92,'📦 Registro'!$A$4:$A$103,0))),"")} | G92: {=IFERROR(IF(I92="","",INDEX('📦 Registro'!$N$4:$N$103,MATCH(I92,'📦 Registro'!$A$4:$A$103,0))),"")} | H92: =IFERROR(IF(F92="","",TODAY()-F92),"") | I92: {=IFERROR(INDEX(#REF!,MATCH(SMALL(IF(#REF!<>"",ROW(#REF!)-3),89),#REF!,0)),"")}
A93: {=IFERROR(IF(I93="","",INDEX('📦 Registro'!$A$4:$A$103,MATCH(I93,'📦 Registro'!$A$4:$A$103,0))),"")} | B93: {=IFERROR(IF(I93="","",INDEX('📦 Registro'!$B$4:$B$103,MATCH(I93,'📦 Registro'!$A$4:$A$103,0))),"")} | C93: {=IFERROR(IF(I93="","",INDEX('📦 Registro'!$D$4:$D$103,MATCH(I93,'📦 Registro'!$A$4:$A$103,0))),"")} | D93: {=IFERROR(IF(I93="","",INDEX('📦 Registro'!$E$4:$E$103,MATCH(I93,'📦 Registro'!$A$4:$A$103,0))),"")} | E93: {=IFERROR(IF(I93="","",INDEX('📦 Registro'!$I$4:$I$103,MATCH(I93,'📦 Registro'!$A$4:$A$103,0))),"")} | F93: {=IFERROR(IF(I93="","",INDEX('📦 Registro'!$C$4:$C$103,MATCH(I93,'📦 Registro'!$A$4:$A$103,0))),"")} | G93: {=IFERROR(IF(I93="","",INDEX('📦 Registro'!$N$4:$N$103,MATCH(I93,'📦 Registro'!$A$4:$A$103,0))),"")} | H93: =IFERROR(IF(F93="","",TODAY()-F93),"") | I93: {=IFERROR(INDEX(#REF!,MATCH(SMALL(IF(#REF!<>"",ROW(#REF!)-3),90),#REF!,0)),"")}
A94: {=IFERROR(IF(I94="","",INDEX('📦 Registro'!$A$4:$A$103,MATCH(I94,'📦 Registro'!$A$4:$A$103,0))),"")} | B94: {=IFERROR(IF(I94="","",INDEX('📦 Registro'!$B$4:$B$103,MATCH(I94,'📦 Registro'!$A$4:$A$103,0))),"")} | C94: {=IFERROR(IF(I94="","",INDEX('📦 Registro'!$D$4:$D$103,MATCH(I94,'📦 Registro'!$A$4:$A$103,0))),"")} | D94: {=IFERROR(IF(I94="","",INDEX('📦 Registro'!$E$4:$E$103,MATCH(I94,'📦 Registro'!$A$4:$A$103,0))),"")} | E94: {=IFERROR(IF(I94="","",INDEX('📦 Registro'!$I$4:$I$103,MATCH(I94,'📦 Registro'!$A$4:$A$103,0))),"")} | F94: {=IFERROR(IF(I94="","",INDEX('📦 Registro'!$C$4:$C$103,MATCH(I94,'📦 Registro'!$A$4:$A$103,0))),"")} | G94: {=IFERROR(IF(I94="","",INDEX('📦 Registro'!$N$4:$N$103,MATCH(I94,'📦 Registro'!$A$4:$A$103,0))),"")} | H94: =IFERROR(IF(F94="","",TODAY()-F94),"") | I94: {=IFERROR(INDEX(#REF!,MATCH(SMALL(IF(#REF!<>"",ROW(#REF!)-3),91),#REF!,0)),"")}
A95: {=IFERROR(IF(I95="","",INDEX('📦 Registro'!$A$4:$A$103,MATCH(I95,'📦 Registro'!$A$4:$A$103,0))),"")} | B95: {=IFERROR(IF(I95="","",INDEX('📦 Registro'!$B$4:$B$103,MATCH(I95,'📦 Registro'!$A$4:$A$103,0))),"")} | C95: {=IFERROR(IF(I95="","",INDEX('📦 Registro'!$D$4:$D$103,MATCH(I95,'📦 Registro'!$A$4:$A$103,0))),"")} | D95: {=IFERROR(IF(I95="","",INDEX('📦 Registro'!$E$4:$E$103,MATCH(I95,'📦 Registro'!$A$4:$A$103,0))),"")} | E95: {=IFERROR(IF(I95="","",INDEX('📦 Registro'!$I$4:$I$103,MATCH(I95,'📦 Registro'!$A$4:$A$103,0))),"")} | F95: {=IFERROR(IF(I95="","",INDEX('📦 Registro'!$C$4:$C$103,MATCH(I95,'📦 Registro'!$A$4:$A$103,0))),"")} | G95: {=IFERROR(IF(I95="","",INDEX('📦 Registro'!$N$4:$N$103,MATCH(I95,'📦 Registro'!$A$4:$A$103,0))),"")} | H95: =IFERROR(IF(F95="","",TODAY()-F95),"") | I95: {=IFERROR(INDEX(#REF!,MATCH(SMALL(IF(#REF!<>"",ROW(#REF!)-3),92),#REF!,0)),"")}
A96: {=IFERROR(IF(I96="","",INDEX('📦 Registro'!$A$4:$A$103,MATCH(I96,'📦 Registro'!$A$4:$A$103,0))),"")} | B96: {=IFERROR(IF(I96="","",INDEX('📦 Registro'!$B$4:$B$103,MATCH(I96,'📦 Registro'!$A$4:$A$103,0))),"")} | C96: {=IFERROR(IF(I96="","",INDEX('📦 Registro'!$D$4:$D$103,MATCH(I96,'📦 Registro'!$A$4:$A$103,0))),"")} | D96: {=IFERROR(IF(I96="","",INDEX('📦 Registro'!$E$4:$E$103,MATCH(I96,'📦 Registro'!$A$4:$A$103,0))),"")} | E96: {=IFERROR(IF(I96="","",INDEX('📦 Registro'!$I$4:$I$103,MATCH(I96,'📦 Registro'!$A$4:$A$103,0))),"")} | F96: {=IFERROR(IF(I96="","",INDEX('📦 Registro'!$C$4:$C$103,MATCH(I96,'📦 Registro'!$A$4:$A$103,0))),"")} | G96: {=IFERROR(IF(I96="","",INDEX('📦 Registro'!$N$4:$N$103,MATCH(I96,'📦 Registro'!$A$4:$A$103,0))),"")} | H96: =IFERROR(IF(F96="","",TODAY()-F96),"") | I96: {=IFERROR(INDEX(#REF!,MATCH(SMALL(IF(#REF!<>"",ROW(#REF!)-3),93),#REF!,0)),"")}
A97: {=IFERROR(IF(I97="","",INDEX('📦 Registro'!$A$4:$A$103,MATCH(I97,'📦 Registro'!$A$4:$A$103,0))),"")} | B97: {=IFERROR(IF(I97="","",INDEX('📦 Registro'!$B$4:$B$103,MATCH(I97,'📦 Registro'!$A$4:$A$103,0))),"")} | C97: {=IFERROR(IF(I97="","",INDEX('📦 Registro'!$D$4:$D$103,MATCH(I97,'📦 Registro'!$A$4:$A$103,0))),"")} | D97: {=IFERROR(IF(I97="","",INDEX('📦 Registro'!$E$4:$E$103,MATCH(I97,'📦 Registro'!$A$4:$A$103,0))),"")} | E97: {=IFERROR(IF(I97="","",INDEX('📦 Registro'!$I$4:$I$103,MATCH(I97,'📦 Registro'!$A$4:$A$103,0))),"")} | F97: {=IFERROR(IF(I97="","",INDEX('📦 Registro'!$C$4:$C$103,MATCH(I97,'📦 Registro'!$A$4:$A$103,0))),"")} | G97: {=IFERROR(IF(I97="","",INDEX('📦 Registro'!$N$4:$N$103,MATCH(I97,'📦 Registro'!$A$4:$A$103,0))),"")} | H97: =IFERROR(IF(F97="","",TODAY()-F97),"") | I97: {=IFERROR(INDEX(#REF!,MATCH(SMALL(IF(#REF!<>"",ROW(#REF!)-3),94),#REF!,0)),"")}
A98: {=IFERROR(IF(I98="","",INDEX('📦 Registro'!$A$4:$A$103,MATCH(I98,'📦 Registro'!$A$4:$A$103,0))),"")} | B98: {=IFERROR(IF(I98="","",INDEX('📦 Registro'!$B$4:$B$103,MATCH(I98,'📦 Registro'!$A$4:$A$103,0))),"")} | C98: {=IFERROR(IF(I98="","",INDEX('📦 Registro'!$D$4:$D$103,MATCH(I98,'📦 Registro'!$A$4:$A$103,0))),"")} | D98: {=IFERROR(IF(I98="","",INDEX('📦 Registro'!$E$4:$E$103,MATCH(I98,'📦 Registro'!$A$4:$A$103,0))),"")} | E98: {=IFERROR(IF(I98="","",INDEX('📦 Registro'!$I$4:$I$103,MATCH(I98,'📦 Registro'!$A$4:$A$103,0))),"")} | F98: {=IFERROR(IF(I98="","",INDEX('📦 Registro'!$C$4:$C$103,MATCH(I98,'📦 Registro'!$A$4:$A$103,0))),"")} | G98: {=IFERROR(IF(I98="","",INDEX('📦 Registro'!$N$4:$N$103,MATCH(I98,'📦 Registro'!$A$4:$A$103,0))),"")} | H98: =IFERROR(IF(F98="","",TODAY()-F98),"") | I98: {=IFERROR(INDEX(#REF!,MATCH(SMALL(IF(#REF!<>"",ROW(#REF!)-3),95),#REF!,0)),"")}
A99: {=IFERROR(IF(I99="","",INDEX('📦 Registro'!$A$4:$A$103,MATCH(I99,'📦 Registro'!$A$4:$A$103,0))),"")} | B99: {=IFERROR(IF(I99="","",INDEX('📦 Registro'!$B$4:$B$103,MATCH(I99,'📦 Registro'!$A$4:$A$103,0))),"")} | C99: {=IFERROR(IF(I99="","",INDEX('📦 Registro'!$D$4:$D$103,MATCH(I99,'📦 Registro'!$A$4:$A$103,0))),"")} | D99: {=IFERROR(IF(I99="","",INDEX('📦 Registro'!$E$4:$E$103,MATCH(I99,'📦 Registro'!$A$4:$A$103,0))),"")} | E99: {=IFERROR(IF(I99="","",INDEX('📦 Registro'!$I$4:$I$103,MATCH(I99,'📦 Registro'!$A$4:$A$103,0))),"")} | F99: {=IFERROR(IF(I99="","",INDEX('📦 Registro'!$C$4:$C$103,MATCH(I99,'📦 Registro'!$A$4:$A$103,0))),"")} | G99: {=IFERROR(IF(I99="","",INDEX('📦 Registro'!$N$4:$N$103,MATCH(I99,'📦 Registro'!$A$4:$A$103,0))),"")} | H99: =IFERROR(IF(F99="","",TODAY()-F99),"") | I99: {=IFERROR(INDEX(#REF!,MATCH(SMALL(IF(#REF!<>"",ROW(#REF!)-3),96),#REF!,0)),"")}
A100: {=IFERROR(IF(I100="","",INDEX('📦 Registro'!$A$4:$A$103,MATCH(I100,'📦 Registro'!$A$4:$A$103,0))),"")} | B100: {=IFERROR(IF(I100="","",INDEX('📦 Registro'!$B$4:$B$103,MATCH(I100,'📦 Registro'!$A$4:$A$103,0))),"")} | C100: {=IFERROR(IF(I100="","",INDEX('📦 Registro'!$D$4:$D$103,MATCH(I100,'📦 Registro'!$A$4:$A$103,0))),"")} | D100: {=IFERROR(IF(I100="","",INDEX('📦 Registro'!$E$4:$E$103,MATCH(I100,'📦 Registro'!$A$4:$A$103,0))),"")} | E100: {=IFERROR(IF(I100="","",INDEX('📦 Registro'!$I$4:$I$103,MATCH(I100,'📦 Registro'!$A$4:$A$103,0))),"")} | F100: {=IFERROR(IF(I100="","",INDEX('📦 Registro'!$C$4:$C$103,MATCH(I100,'📦 Registro'!$A$4:$A$103,0))),"")} | G100: {=IFERROR(IF(I100="","",INDEX('📦 Registro'!$N$4:$N$103,MATCH(I100,'📦 Registro'!$A$4:$A$103,0))),"")} | H100: =IFERROR(IF(F100="","",TODAY()-F100),"") | I100: {=IFERROR(INDEX(#REF!,MATCH(SMALL(IF(#REF!<>"",ROW(#REF!)-3),97),#REF!,0)),"")}
...

Sheet 📊 Dashboard
A1: 📊 RESUMEN DEL NEGOCIO
A3: En Stock | C3: Vendidos | E3: Total Comprados
A4: =COUNTA('📋 Stock Activo'!A4:A102) -> 98 | C4: =COUNTA('📦 Registro'!O4:O103) -> 10 | E4: =COUNTA('📦 Registro'!L4:L103) -> 19
A6: Total Invertido | C6: Total Recaudado | E6: Ganancia Total
A7: =IFERROR(SUM('📦 Registro'!N4:N103),0) -> 3654000 | C7: =IFERROR(SUM('📦 Registro'!Q4:Q103),0) -> 2011000 | E7: =IFERROR(SUM('📦 Registro'!S4:S103),0) -> 567000
A9: 📦 STOCK POR CATEGORÍA
A10: Categoría | B10: En Stock | C10: Vendidos | D10: Invertido Total | E10: Recaudado | F10: Ganancia
A11: Notebook | B11: =COUNTIFS('📦 Registro'!$B$4:$B$103,A11,'📦 Registro'!$O$4:$O$103,"") -> 3 | C11: =COUNTIFS('📦 Registro'!$B$4:$B$103,A11,'📦 Registro'!$O$4:$O$103,"<>") -> 1 | D11: =IFERROR(SUMIF('📦 Registro'!$B$4:$B$103,A11,'📦 Registro'!$N$4:$N$103),0) -> 1584000 | E11: =IFERROR(SUMIF('📦 Registro'!$B$4:$B$103,A11,'📦 Registro'!$Q$4:$Q$103),0) -> 300000 | F11: =IFERROR(SUMIF('📦 Registro'!$B$4:$B$103,A11,'📦 Registro'!$S$4:$S$103),0) -> 96000
A12: Computador | B12: =COUNTIFS('📦 Registro'!$B$4:$B$103,A12,'📦 Registro'!$O$4:$O$103,"") -> 3 | C12: =COUNTIFS('📦 Registro'!$B$4:$B$103,A12,'📦 Registro'!$O$4:$O$103,"<>") -> 1 | D12: =IFERROR(SUMIF('📦 Registro'!$B$4:$B$103,A12,'📦 Registro'!$N$4:$N$103),0) -> 910000 | E12: =IFERROR(SUMIF('📦 Registro'!$B$4:$B$103,A12,'📦 Registro'!$Q$4:$Q$103),0) -> 361000 | F12: =IFERROR(SUMIF('📦 Registro'!$B$4:$B$103,A12,'📦 Registro'!$S$4:$S$103),0) -> 151000
A13: TV | B13: =COUNTIFS('📦 Registro'!$B$4:$B$103,A13,'📦 Registro'!$O$4:$O$103,"") -> 0 | C13: =COUNTIFS('📦 Registro'!$B$4:$B$103,A13,'📦 Registro'!$O$4:$O$103,"<>") -> 0 | D13: =IFERROR(SUMIF('📦 Registro'!$B$4:$B$103,A13,'📦 Registro'!$N$4:$N$103),0) -> 0 | E13: =IFERROR(SUMIF('📦 Registro'!$B$4:$B$103,A13,'📦 Registro'!$Q$4:$Q$103),0) -> 0 | F13: =IFERROR(SUMIF('📦 Registro'!$B$4:$B$103,A13,'📦 Registro'!$S$4:$S$103),0) -> 0
A14: Tablet | B14: =COUNTIFS('📦 Registro'!$B$4:$B$103,A14,'📦 Registro'!$O$4:$O$103,"") -> 0 | C14: =COUNTIFS('📦 Registro'!$B$4:$B$103,A14,'📦 Registro'!$O$4:$O$103,"<>") -> 0 | D14: =IFERROR(SUMIF('📦 Registro'!$B$4:$B$103,A14,'📦 Registro'!$N$4:$N$103),0) -> 0 | E14: =IFERROR(SUMIF('📦 Registro'!$B$4:$B$103,A14,'📦 Registro'!$Q$4:$Q$103),0) -> 0 | F14: =IFERROR(SUMIF('📦 Registro'!$B$4:$B$103,A14,'📦 Registro'!$S$4:$S$103),0) -> 0
A15: Audífonos | B15: =COUNTIFS('📦 Registro'!$B$4:$B$103,A15,'📦 Registro'!$O$4:$O$103,"") -> 0 | C15: =COUNTIFS('📦 Registro'!$B$4:$B$103,A15,'📦 Registro'!$O$4:$O$103,"<>") -> 0 | D15: =IFERROR(SUMIF('📦 Registro'!$B$4:$B$103,A15,'📦 Registro'!$N$4:$N$103),0) -> 0 | E15: =IFERROR(SUMIF('📦 Registro'!$B$4:$B$103,A15,'📦 Registro'!$Q$4:$Q$103),0) -> 0 | F15: =IFERROR(SUMIF('📦 Registro'!$B$4:$B$103,A15,'📦 Registro'!$S$4:$S$103),0) -> 0
A16: Consola | B16: =COUNTIFS('📦 Registro'!$B$4:$B$103,A16,'📦 Registro'!$O$4:$O$103,"") -> 0 | C16: =COUNTIFS('📦 Registro'!$B$4:$B$103,A16,'📦 Registro'!$O$4:$O$103,"<>") -> 0 | D16: =IFERROR(SUMIF('📦 Registro'!$B$4:$B$103,A16,'📦 Registro'!$N$4:$N$103),0) -> 0 | E16: =IFERROR(SUMIF('📦 Registro'!$B$4:$B$103,A16,'📦 Registro'!$Q$4:$Q$103),0) -> 0 | F16: =IFERROR(SUMIF('📦 Registro'!$B$4:$B$103,A16,'📦 Registro'!$S$4:$S$103),0) -> 0
A17: Smartphone | B17: =COUNTIFS('📦 Registro'!$B$4:$B$103,A17,'📦 Registro'!$O$4:$O$103,"") -> 2 | C17: =COUNTIFS('📦 Registro'!$B$4:$B$103,A17,'📦 Registro'!$O$4:$O$103,"<>") -> 8 | D17: =IFERROR(SUMIF('📦 Registro'!$B$4:$B$103,A17,'📦 Registro'!$N$4:$N$103),0) -> 1110000 | E17: =IFERROR(SUMIF('📦 Registro'!$B$4:$B$103,A17,'📦 Registro'!$Q$4:$Q$103),0) -> 1350000 | F17: =IFERROR(SUMIF('📦 Registro'!$B$4:$B$103,A17,'📦 Registro'!$S$4:$S$103),0) -> 320000
A18: Otro | B18: =COUNTIFS('📦 Registro'!$B$4:$B$103,A18,'📦 Registro'!$O$4:$O$103,"") -> 0 | C18: =COUNTIFS('📦 Registro'!$B$4:$B$103,A18,'📦 Registro'!$O$4:$O$103,"<>") -> 0 | D18: =IFERROR(SUMIF('📦 Registro'!$B$4:$B$103,A18,'📦 Registro'!$N$4:$N$103),0) -> 0 | E18: =IFERROR(SUMIF('📦 Registro'!$B$4:$B$103,A18,'📦 Registro'!$Q$4:$Q$103),0) -> 0 | F18: =IFERROR(SUMIF('📦 Registro'!$B$4:$B$103,A18,'📦 Registro'!$S$4:$S$103),0) -> 0

Sheet 📖 Guía
A1: 📖 GUÍA DE USO
A3: PASO | B3: CAMPO | C3: QUÉ INGRESAR
A4: 1 | B4: Categoría | C4: Tipo de equipo: Notebook, TV, Tablet, Audífonos, Consola, etc.
A5: 2 | B5: Fecha Compra | C5: Fecha en que compraste (DD/MM/AAAA)
A6: 3 | B6: Equipo | C6: Nombre descriptivo: ej. 'MacBook Air M2 8GB 256GB Gris'
A7: 4 | B7: Marca / Modelo | C7: Marca y número de modelo específico
A8: 5 | B8: IMEI / S/N | C8: Celulares: IMEI. Notebooks/TV/otros: número de serie
A9: 6 | B9: Estado | C9: Menú: Nuevo / Como nuevo / Bueno / Regular / Con falla
A10: 7 | B10: Proveedor | C10: Nombre o alias de quien te vendió
A11: 8 | B11: Precio Compra | C11: Lo que pagaste (solo número, sin puntos ni $)
A12: 9 | B12: Gastos Extra | C12: Reparaciones, accesorios, flete, etc.
A13: 10 | B13: Costo Total | C13: ✅ Se calcula solo
A14: 11 | B14: Fecha Venta | C14: Llenar SOLO cuando se concrete la venta
... A17: 14 | B17: Ganancia Neta | C17: ✅ Se calcula sola
A19: ⚠️ CÓMO FUNCIONA EL STOCK
B20: Cómo funciona | C20: Al dejar Fecha Venta vacía → aparece en 📋 Stock Activo automáticamente.
B21: Venta concretada | C21: Al llenar Fecha Venta → desaparece del stock automáticamente.
B22: Días en stock | C22: El stock muestra cuántos días lleva cada equipo sin vender.
B23: Alerta amarilla | C23: 30+ días sin vender → considera bajar el precio.
B24: Alerta roja | C24: 60+ días sin vender → revisa la estrategia de venta.
A26: 💡 CONSEJOS PRÁCTICOS
B27: IMEI siempre | C27: Para celulares, anota el IMEI. Protección legal ante robos.
B28: Gastos extra | C28: Incluye TODO: pantalla, cargador, transporte al comprar.
B29: Respaldo | C29: Guarda el archivo en Google Drive para acceso desde el celular.
